Workbook

Sheet RESUMEN 2026 
A1: PROYECTOS | B1: ENERO | C1: FEBRERO | D1: MARZO | E1: ABRIL | F1: MAYO | G1: JUNIO | H1: JULIO | I1: AGOSTO | J1: SEPTIEMBRE | K1: OCTUBRE | L1: NOVIEMBRE | M1: DICIEMBRE | N1: TOTAL
A2: RAMIRO LEE | B2: 1759610.2 | C2: 1031773.4 | D2: 1510851.5 | E2: 675669.69 | F2: 3877.12 | N2: =SUM(B2:M2) -> 4981782
A3: CELESTE LANDA | B3: 94927.06 | C3: 1183044.6 | D3: 789150.24 | E3: 644857 | F3: 42531.61 | N3: =SUM(B3:M3) -> 2754510.5
A4: ALFREDO PALOMINO | B4: 672141.68 | C4: 115487.71 | D4: 529974.98 | E4: 43494.83 | F4: 51126.195 | N4: =SUM(B4:M4) -> 1412225.4
A5: HECTOR VELA | B5: 585963.89 | C5: 97086.59 | D5: 368420.85 | E5: 178360.14 | F5: 253025.72 | N5: =SUM(B5:M5) -> 1482857.2
A6: ORLANDO MARTINEZ | B6: 3900 | C6: 12000 | D6: 67881.717 | E6: 217248.35 | F6: 103280.53 | N6: =SUM(B6:M6) -> 404310.6
A7: ANA MARGARITA SAHAGUN | B7: 0 | C7: 0 | D7: 0 | E7: 32533.56 | F7: 5832.61 | N7: =SUM(B7:M7) -> 38366.17
B8: =SUM(B2:B7) -> 3116542.9 | C8: =SUM(C2:C7) -> 2439392.4 | D8: =SUM(D2:D7) -> 3266279.3 | E8: =SUM(E2:E7) -> 1792163.6 | F8: =SUM(F2:F7) -> 459673.79 | G8: =SUM(G2:G7) -> 0 | H8: =SUM(H2:H7) -> 0 | I8: =SUM(I2:I7) -> 0 | ... N8: =SUM(N2:N7) -> 11074052
A9: PUNTO DE VENTA | B9: ENERO | C9: FEBRERO | D9: MARZO | E9: ABRIL | F9: MAYO | G9: JUNIO | H9: JULIO | I9: AGOSTO | J9: SEPTIEMBRE | K9: OCTUBRE | L9: NOVIEMBRE | M9: DICIEMBRE | N9: TOTAL
A10: TIENDA | B10: 418711.75 | C10: 431563.95 | D10: 408072.15 | E10: 194487.44 | F10: 193901.46 | N10: =SUM(B10:M10) -> 1646736.8
A11: TOTAL | B11: =+B8+B10 -> 3535254.6 | C11: =+C8+C10 -> 2870956.3 | D11: =+D8+D10 -> 3674351.5 | E11: =+E8+E10 -> 1986651 | F11: =+F8+F10 -> 653575.25 | G11: =+G8+G10 -> 0 | H11: =+H8+H10 -> 0 | I11: =+I8+I10 -> 0 | ... N11: =+N8+N10 -> 12720789
A13: VENTAS TOTALES CONSOLIDADAS 2026
A14: MES | B14: VENTAS PROYECTOS | C14: MATERIAL REAL | D14: UT. BRUTA PROYECTOS | E14: GASTOS PROYECTOS | F14: UTILIDAD NETA PROYECTOS | G14: VENTAS TIENDA | H14: UT. BRUTA TIENDA | I14: GASTOS TIENDA | J14: UTILIDAD NETA TIENDA | K14: VENTAS TOTAL | L14: UTILIDAD BRUTA TOTAL | M14: UTILIDAD NETA TOTAL
A15: ENERO | B15: =+B8 -> 3116542.9 | C15: 1216281 | D15: =+B15-C15 -> 1900261.9 | E15: =1660050.33-98085.65 -> 1561964.7 | F15: =+D15-E15 -> 338297.22 | G15: =+B10 -> 418711.75 | H15: 76766.16 | I15: 98085.65 | J15: =+H15-I15 -> -21319.49 | K15: =+B15+G15 -> 3535254.6 | L15: =+D15+H15 -> 1977028.1 | M15: =+F15+J15 -> 316977.73
A16: FEBRERO | B16: =+C8 -> 2439392.4 | C16: 1113152.6 | D16: =+B16-C16 -> 1326239.7 | E16: =1259904.05-104434.14 -> 1155469.9 | F16: =+D16-E16 -> 170769.82 | G16: =+C10 -> 431563.95 | H16: 78871.49 | I16: 104434.14 | J16: =+H16-I16 -> -25562.65 | K16: =+B16+G16 -> 2870956.3 | L16: =+D16+H16 -> 1405111.2 | M16: =+F16+J16 -> 145207.17
A17: MARZO | B17: =+D8 -> 3266279.3 | C17: 1608971.7 | D17: =+B17-C17 -> 1657307.6 | E17: =1350532.52-86532.88 -> 1263999.6 | F17: =+D17-E17 -> 393308 | G17: =+D10 -> 408072.15 | H17: 72828.24 | I17: 86532.88 | J17: =+H17-I17 -> -13704.64 | K17: =+B17+G17 -> 3674351.5 | L17: =+D17+H17 -> 1730135.9 | M17: =+F17+J17 -> 379603.36
A18: ABRIL | B18: =+E8 -> 1792163.6 | C18: 788704.2 | D18: =+B18-C18 -> 1003459.4 | E18: =1219130.53-74375.32 -> 1144755.2 | F18: =+D18-E18 -> -141295.83 | G18: =+E10 -> 194487.44 | H18: 37490.92 | I18: 74375.32 | J18: =+H18-I18 -> -36884.4 | K18: =+B18+G18 -> 1986651 | L18: =+D18+H18 -> 1040950.3 | M18: =+F18+J18 -> -178180.23
A19: MAYO | B19: =+F8 -> 459673.79 | C19: 291171.06 | D19: =+B19-C19 -> 168502.72 | E19: =1266003.31-66678.87 -> 1199324.4 | F19: =+D19-E19 -> -1030821.7 | G19: 193901.46 | H19: 39887.94 | I19: 66678.87 | J19: =+H19-I19 -> -26790.93 | K19: =+B19+G19 -> 653575.25 | L19: =+D19+H19 -> 208390.66 | M19: =+F19+J19 -> -1057612.6
A20: JUNIO | D20: =+B20-C20 -> 0 | F20: =+D20-E20 -> 0 | J20: =+H20-I20 -> 0 | K20: =+B20+G20 -> 0 | L20: =+D20+H20 -> 0 | M20: =+F20+J20 -> 0
A21: JULIO | D21: =+B21-C21 -> 0 | F21: =+D21-E21 -> 0 | J21: =+H21-I21 -> 0 | K21: =+B21+G21 -> 0 | L21: =+D21+H21 -> 0 | M21: =+F21+J21 -> 0
A22: AGOSTO | D22: =+B22-C22 -> 0 | F22: =+D22-E22 -> 0 | J22: =+H22-I22 -> 0 | K22: =+B22+G22 -> 0 | L22: =+D22+H22 -> 0 | M22: =+F22+J22 -> 0
A23: SEPTIEMBRE | D23: =+B23-C23 -> 0 | F23: =+D23-E23 -> 0 | J23: =+H23-I23 -> 0 | K23: =+B23+G23 -> 0 | L23: =+D23+H23 -> 0 | M23: =+F23+J23 -> 0
A24: OCTUBRE | D24: =+B24-C24 -> 0 | F24: =+D24-E24 -> 0 | J24: =+H24-I24 -> 0 | K24: =+B24+G24 -> 0 | L24: =+D24+H24 -> 0 | M24: =+F24+J24 -> 0
A25: NOVIEMBRE | D25: =+B25-C25 -> 0 | F25: =+D25-E25 -> 0 | J25: =+H25-I25 -> 0 | K25: =+B25+G25 -> 0 | L25: =+D25+H25 -> 0 | M25: =+F25+J25 -> 0
A26: DICIEMBRE | D26: =+B26-C26 -> 0 | F26: =+D26-E26 -> 0 | J26: =+H26-I26 -> 0 | K26: =+B26+G26 -> 0 | L26: =+D26+H26 -> 0 | M26: =+F26+J26 -> 0
A27: TOTAL | B27: =SUM(B15:B26) -> 11074052 | C27: =SUM(C15:C26) -> 5018280.5 | D27: =SUM(D15:D26) -> 6055771.4 | E27: =SUM(E15:E26) -> 6325513.9 | F27: =SUM(F15:F26) -> -269742.51 | G27: =SUM(G15:G26) -> 1646736.8 | H27: =SUM(H15:H26) -> 305844.75 | I27: =SUM(I15:I26) -> 430106.86 | ... M27: =SUM(M15:M26) -> -394004.62
C28: =+C27/B27 -> 0.45315667 | D28: =+D27/B27 -> 0.54684333 | E28: =+E27/B27 -> 0.57120139 | F28: =+F27/B27 -> -0.024358068 | H28: =+H27/G27 -> 0.18572777 | I28: =+I27/G27 -> 0.26118738 | J28: =+J27/G27 -> -0.075459608 | L28: =+L27/K27 -> 0.50009605 | M28: =+M27/K27 -> -0.030973285

Sheet VENTAS POR ASESOR
A1: 46023
A2: TC PROMEDIO | B2: 17.6768 | D2: META 2026 | E2: 770000 | H2: CLIENTE | I2: ENERO | J2: FEBRERO | K2: MARZO | L2: ABRIL | M2: MAYO | N2: TOTAL
H3: CORNING OPTICAL COMMUNICATIONS | I3: 1214337.5 | J3: 1001907 | K3: 1437379.5 | L3: 417842.68 | M3: 5832.61 | N3: =SUM(I3:M3) -> 4077299.3
A4: Promotor | B4: MXN | C4: USD | D4: Suma total | E4: META | F4: COMISIONES | G4: FECHA DE PAGO | H4: EMERSON TOOL AND APPLIANCE COMPANY | I4: 57980.51 | J4: 651474.53 | K4: =33540.16*17.7575 -> 595589.39 | L4: =168092.2+4280.09*17.6969 -> 243836.52 | N4: =SUM(I4:M4) -> 1548881
A5: ALFREDO PALOMINO | B5: 276319.52 | C5: 21281.48 | D5: =B5+'ENERO '!I39 -> 672141.68 | E5: =+D5-E2 -> -97858.318 | H5: ALCOM ELECTRONICOS DE MEXICO | I5: 265464.77 | J5: 105070.24 | K5: 393603.79 | L5: 30815.16 | M5: 103057.61 | N5: =SUM(I5:M5) -> 898011.57
A6: CELESTE LANDA | B6: 94927.06 | D6: =B6+C6*$B$2 -> 94927.06 | E6: =+D6-E2 -> -675072.94 | H6: BCS-AIS ENSAMBLES MEXICO | I6: 6143.36 | J6: 377670.11 | K6: 106943.39 | L6: 173073.75 | N6: =SUM(I6:M6) -> 663830.61
A7: HECTOR VELA | B7: 585963.89 | D7: =B7+C7*$B$2 -> 585963.89 | E7: =+D7-E2 -> -184036.11 | H7: CORNING MONTERREY | I7: 522366.4 | K7: 64786.89 | L7: 73722.85 | N7: =SUM(I7:M7) -> 660876.14
A8: ORLANDO MARTINEZ | B8: 3900 | D8: =B8+C8*$B$2 -> 3900 | E8: =+D8-E2 -> -766100 | H8: IMPRESORA DONNECO INTERNACIONAL | I8: 146667.55 | K8: 172166.9 | L8: 69949.26 | M8: 8670.47 | N8: =SUM(I8:M8) -> 397454.18
A9: RAMIRO LEE | B9: 1759610.2 | D9: =B9+C9*$B$2 -> 1759610.2 | E9: =+D9-E2 -> 989610.24 | H9: IIMED MEDICAL SOLUTIONS LLC | I9: 376188.47 | J9: 7666.0379 | L9: 0 | N9: =SUM(I9:M9) -> 383854.5
A10: Suma total | B10: 2720720.7 | C10: 21281.48 | D10: =SUM(D5:D9) -> 3116542.9 | H10: NEWOPTIX RS | I10: 306878.08 | L10: 0 | N10: =SUM(I10:M10) -> 306878.08
H11: E&M INDUSTRIAL SUPPLIES | I11: 2387.29 | J11: 43474.82 | L11: 206387.19 | M11: 7140.41 | N11: =SUM(I11:M11) -> 259389.71
A12: 46054 | H12: PUBLICO EN GENERAL | K12: 21161.42 | L12: 204576.2 | N12: =SUM(I12:M12) -> 225737.62
A13: TC PROMEDIO | B13: 17.2286 | H13: CARPLASTIC | J13: 14513 | K13: 31800 | L13: 12460 | M13: 131414.4 | N13: =SUM(I13:M13) -> 190187.4
A14: Promotor | B14: MXN | C14: USD | D14: Total general | E14: META | F14: COMISIONES | G14: FECHA DE PAGO | H14: ALPS ALPINE NORTH AMERICA | J14: 11151.9 | K14: =8082.4*17.7575 -> 143523.22 | L14: 0 | M14: 7351.1452 | N14: =SUM(I14:M14) -> 162026.26
A15: ALFREDO PALOMINO | B15: 96228.11 | C15: 1092.25 | D15: =+B15+FEBRERO!I40 -> 115487.71 | E15: =+D15-$E$2 -> -654512.29 | H15: LANDIS & GYR | J15: 16815.47 | K15: 121920.27 | L15: 15747 | N15: =SUM(I15:M15) -> 154482.74
A16: CELESTE LANDA | B16: 430377.91 | C16: 38547.63 | D16: =+B16+FEBRERO!I41 -> 1183044.6 | E16: =+D16-$E$2 -> 413044.62 | F16: 24996.413 | G16: 46136 | H16: AUTOMOTIVE MAQUILADORA | I16: 3788.24 | J16: 23031.26 | L16: 80001.6 | M16: 3788.24 | N16: =SUM(I16:M16) -> 110609.34
A17: HECTOR VELA | B17: 97086.59 | D17: =+B17+C17*$B$13 -> 97086.59 | E17: =+D17-$E$2 -> -672913.41 | H17: HOFFMAN SCHROFF MANUFACTURING | I17: 36175.29 | J17: 7167.35 | K17: 17624.52 | L17: 7244.42 | M17: 38518.83 | N17: =SUM(I17:M17) -> 106730.41
A18: ORLANDO MARTINEZ | B18: 12000 | D18: =+B18+C18*$B$13 -> 12000 | E18: =+D18-$E$2 -> -758000 | H18: BLACK & DECKER DE REYNOSA | L18: 98714.81 | M18: 88.88 | N18: =SUM(I18:M18) -> 98803.69
A19: RAMIRO LEE | B19: 1031773.4 | D19: =+B19+C19*$B$13 -> 1031773.4 | E19: =+D19-$E$2 -> 261773.43 | H19: MONROE MEXICO | K19: 43213.34 | L19: 34272.99 | M19: 14010.74 | N19: =SUM(I19:M19) -> 91497.07
A20: Suma total | B20: 1667466 | C20: 39639.88 | D20: =SUM(D15:D19) -> 2439392.4 | H20: VEXIN GLOBAL SUPPLY | L20: 72959.46 | M20: 7151.29 | N20: =SUM(I20:M20) -> 80110.75
H21: INTERMEX MANUFACTURA | M21: 65391.56 | N21: =SUM(I21:M21) -> 65391.56
A22: 46082 | H22: CEBAL AMERICAS DE REYNOSA | I22: 17851.85 | J22: 37110.3 | K22: 9920.03 | L22: 0 | N22: =SUM(I22:M22) -> 64882.18
A23: TC PROMEDIO | B23: 17.7575 | H23: SANMINA-SCI DE MEXICO | I23: 48725.74 | L23: 0 | N23: =SUM(I23:M23) -> 48725.74
A24: Promotor | B24: MXN | C24: USD | D24: Total general | E24: META | F24: COMISIONES | G24: FECHA DE PAGO | H24: MIKUNI AMERICAN CORPORATION | J24: 12647.171 | L24: 0 | M24: 35391.2 | N24: =SUM(I24:M24) -> 48038.371
A25: ALFREDO PALOMINO | B25: 402511.39 | C25: 7189.3 | D25: =+B25+MARZO!I43 -> 529974.98 | E25: =+D25-$E$2 -> -240025.02 | H25: BORGWARNER REYNOSA | I25: 23402.58 | J25: 9232.98 | L25: 0 | N25: =SUM(I25:M25) -> 32635.56
A26: CELESTE LANDA | B26: 106943.39 | C26: 33540.16 | D26: =+B26+MARZO!I44 -> 789150.24 | E26: =+D26-$E$2 -> 19150.244 | H26: WOODCRAFTERS HOME PRODUCTS | I26: 14754.75 | L26: 13991.6 | M26: 1471.5 | N26: =SUM(I26:M26) -> 30217.85
A27: HECTOR VELA | B27: 368420.85 | D27: =+B27+C27*$B$23 -> 368420.85 | E27: =+D27-$E$2 -> -401579.15 | H27: AUTOFLETES GOMEZ LEAL | I27: 29665.38 | L27: 0 | N27: =SUM(I27:M27) -> 29665.38
A28: ORLANDO MARTINEZ | B28: 52547.19 | C28: 893.1 | D28: =+B28+MARZO!I45 -> 67881.717 | E28: =+D28-$E$2 -> -702118.28 | H28: MARIA ANTONIETA NUÑEZ PACHECO | M28: 26803.03 | N28: =SUM(I28:M28) -> 26803.03
A29: RAMIRO LEE | B29: 1510851.5 | D29: =+B29+C29*$B$23 -> 1510851.5 | E29: =+D29-$E$2 -> 740851.51 | H29: INDO-MIM MEXICO | J29: 21480.47 | L29: 0 | M29: 1878.67 | N29: =SUM(I29:M29) -> 23359.14
A30: Suma total | B30: =SUM(B25:B29) -> 2441274.3 | C30: =SUM(C25:C29) -> 41622.56 | D30: =SUM(D25:D29) -> 3266279.3 | H30: SMP ENGINE MANAGEMENT | K30: 14989.13 | L30: 0 | N30: =SUM(I30:M30) -> 14989.13
H31: SMP FOUR SEASONS DE MEXICO | I31: 14420.32 | L31: 0 | N31: =SUM(I31:M31) -> 14420.32
A32: 46113 | H32: JOSE LEOPOLDO GARCIA GRACIA | I32: 5013.32 | L32: 5619.64 | N32: =SUM(I32:M32) -> 10632.96
A33: TC PROMEDIO | B33: 17.6969 | H33: CRISTALERA GONZALEZ MORELOS | L33: 7469.14 | N33: =SUM(I33:M33) -> 7469.14
A34: Promotor | B34: MXN | C34: USD | D34: Total general | E34: META | F34: COMISIONES | G34: FECHA DE PAGO | H34: FILTERTEK DE MEXICO | J34: 6835.14 | L34: 0 | N34: =SUM(I34:M34) -> 6835.14
A35: ALFREDO PALOMINO | B35: 43494.83 | C35: 0 | D35: =+B35+C35*$B$33 -> 43494.83 | E35: =+D35-$E$2 -> -726505.17 | H35: BSN MEDICAL | I35: 4697.8 | L35: 0 | N35: =SUM(I35:M35) -> 4697.8
A36: CELESTE LANDA | B36: 557805.11 | C36: 4280.09 | D36: =+B36+ABRIL!I47 -> 644857 | E36: =+D36-$E$2 -> -125143 | H36: CONSORCIO PETROLERO 5M DEL GOLFO | L36: 4632.33 | N36: =SUM(I36:M36) -> 4632.33
A37: HECTOR VELA | B37: 178360.14 | C37: 0 | D37: =+B37+C37*$B$33 -> 178360.14 | E37: =+D37-$E$2 -> -591639.86 | H37: AMETEK LAMB MOTORES DE MEXICO | L37: 3891.08 | N37: =SUM(I37:M37) -> 3891.08
A38: ORLANDO MARTINEZ | B38: 217248.35 | C38: 0 | D38: =+B38+C38*$B$33 -> 217248.35 | E38: =+D38-$E$2 -> -552751.65 | H38: CAL-COMP ELECTRONICS DE MEXICO CO | L38: 3648.32 | N38: =SUM(I38:M38) -> 3648.32
A39: RAMIRO LEE | B39: 675669.69 | C39: 0 | D39: =+B39+C39*$B$33 -> 675669.69 | E39: =+D39-$E$2 -> -94330.31 | H39: MADRAX GREEN AUTOMATION | J39: 3157.87 | L39: 0 | N39: =SUM(I39:M39) -> 3157.87
A40: ANA MARGARITA SAHAGUN | B40: 32533.56 | C40: 0 | D40: =+B40+C40*$B$33 -> 32533.56 | E40: =+D40-$E$2 -> -737466.44 | H40: GM3 INDUSTRIAL SERVICES S. DE R.L. DE C.V | M40: 1712.7 | N40: =SUM(I40:M40) -> 1712.7
A41: Suma total | B41: =SUM(B35:B40) -> 1705111.7 | C41: =SUM(C35:C40) -> 4280.09 | D41: =SUM(D35:D40) -> 1792163.6 | I41: =SUM(I3:I40) -> 3096909.2 | J41: =SUM(J3:J40) -> 2350405.7 | K41: =SUM(K3:K40) -> 3174621.8 | L41: =SUM(L3:L40) -> 1780856 | M41: =SUM(M3:M40) -> 459673.29 | N41: =SUM(N3:N40) -> 10862466
A43: 46143
A44: TC PROMEDIO | B44: 17.3922
A45: Promotor | B45: MXN | C45: USD | D45: Total general | E45: META | F45: COMISIONES | G45: FECHA DE PAGO
A46: ALFREDO PALOMINO | B46: 43775.05 | C46: 426.99 | D46: =+B46+MAYO!J28 -> 51126.195 | E46: =+D46-$E$2 -> -718873.8
A47: CELESTE LANDA | B47: 42531.61 | C47: 0 | D47: =+B47+C47*$B$33 -> 42531.61 | E47: =+D47-$E$2 -> -727468.39
A48: HECTOR VELA | B48: 253025.72 | C48: 0 | D48: =+B48+C48*$B$33 -> 253025.72 | E48: =+D48-$E$2 -> -516974.28
A49: ORLANDO MARTINEZ | B49: 103280.53 | C49: 0 | D49: =+B49+C49*$B$33 -> 103280.53 | E49: =+D49-$E$2 -> -666719.47
A50: RAMIRO LEE | B50: 3877.12 | C50: 0 | D50: =+B50+C50*$B$33 -> 3877.12 | E50: =+D50-$E$2 -> -766122.88
A51: ANA MARGARITA SAHAGUN | B51: 5832.61 | C51: 0 | D51: =+B51+C51*$B$33 -> 5832.61 | E51: =+D51-$E$2 -> -764167.39
A52: Suma total | B52: =SUM(B46:B51) -> 452322.64 | C52: =SUM(C46:C51) -> 426.99 | D52: =SUM(D46:D51) -> 459673.79
D54: =+D52+D41+D30+D20+D10 -> 11074052
D55: =11074059-D54 -> 7.10607

Sheet ENERO 
A1: Id | B1: Promotor | C1: Cliente | D1: Fecha | E1: Descripcion | F1: Moneda | G1: Cotizado cliente | H1: TC | J1: Indirecto presupuestado | K1: Indirecto Real | L1: MO COBRADA | M1: Mano obra real | N1: Material real | P1: Material utilidad | Q1: Mano obra utilidad | R1: Utilidad | S1: Utilidad después de indirectos | T1: % Utilidad antes de indirectos | U1: $ Utilidad a comision | V1: % Utilidad a comision | W1: 0.03
A2: 12862 | B2: CELESTE LANDA | C2: E&M INDUSTRIAL SUPPLIES | D2: 46048 | E2: SOPORTE SITEMA DE ALARMAS | F2: MXN | G2: 2387.29 | H2: 1 | J2: 504.26 | K2: 442.66 | L2: =+M2+Q2 -> 1999.99 | M2: 706.62 | N2: 276.64 | O2: =+N2*H2 -> 276.64 | P2: 110.66 | Q2: 1293.37 | R2: 1404.03 | S2: 961.37 | T2: 61.39 % | U2: 899.77 | V2: 37.69 % | W2: =+U2*0.03 -> 26.9931
A3: 12856 | B3: RAMIRO LEE | C3: BSN MEDICAL | D3: 46051 | E3: P#12856 - OC #228434 - Servicio de adecuación - Pin 2435. | F3: MXN | G3: 4697.8 | H3: 1 | J3: 886.48 | K3: 498.85 | L3: =+M3+Q3 -> 4697.8 | M3: 1185.01 | N3: 0 | O3: =+N3*H3 -> 0 | P3: 0 | Q3: 3512.79 | R3: 3512.79 | S3: 3013.94 | T3: 83.03 % | U3: 2626.31 | V3: 55.91 % | W3: =+U3*0.03 -> 78.7893
A4: 12853 | B4: CELESTE LANDA | C4: BORGWARNER REYNOSA | D4: 46050 | E4: RFQ-S-1101: Instalación de nodo de red para CAT | F4: MXN | G4: 11887.88 | H4: 1 | J4: 1505.11 | K4: 928.18 | L4: =+M4+Q4 -> 8410.32 | M4: 3038.55 | N4: 250.58 | O4: =+N4*H4 -> 250.58 | P4: 3226.98 | Q4: 5371.77 | R4: 8598.75 | S4: 7670.57 | T4: 77.19 % | U4: 7093.64 | V4: 59.67 % | W4: =+U4*0.03 -> 212.8092
A5: 12851 | B5: HECTOR VELA | C5: AUTOFLETES GOMEZ LEAL | D5: 46052 | E5: MANTENIMIENTO DE CCTV PREVENTIVO PATIO DE CONTENEDORES (ADECUACION PARA CABLEADO DE CAMARA DE LA ESQUINA) (Actualizado mano de obra) | F5: MXN | G5: 29665.38 | H5: 1 | J5: 6225.57 | K5: 4852.9 | L5: =+M5+Q5 -> 20820.62 | M5: 4264.66 | N5: 4502.07 | O5: =+N5*H5 -> 4502.07 | P5: 4342.69 | Q5: 16555.96 | R5: 20897.61 | S5: 16044.71 | T5: 75.07 % | U5: 14672.04 | V5: 49.46 % | W5: =+U5*0.03 -> 440.1612
A6: 12840 | B6: HECTOR VELA | C6: HOFFMAN SCHROFF MANUFACTURING | D6: 46045 | E6: VENTA DE MOCHILA SWISSGEAR 5358 LAPTOP BACKPACK / VENTILADOR Y SOPORTE PARA LAPTOP LUZ LED 9" A 17" (actualizado) | F6: MXN | G6: 9486.36 | H6: 1 | J6: 1190.53 | K6: 1126.71 | L6: =+M6+Q6 -> 0 | M6: 0 | N6: 5590.08 | O6: =+N6*H6 -> 5590.08 | P6: 3896.28 | Q6: 0 | R6: 3896.28 | S6: 2769.57 | T6: 41.75 % | U6: 2705.75 | V6: 28.52 % | W6: =+U6*0.03 -> 81.1725
A7: 12828 | B7: CELESTE LANDA | C7: JOSE LEOPOLDO GARCIA GRACIA | D7: 46045 | E7: 508K1 OXXO TRAREYSA | F7: MXN | G7: 5013.32 | H7: 1 | J7: 513.85 | K7: 419.27 | L7: 0 | M7: 806.1 | N7: 0 | O7: =+N7*H7 -> 0 | P7: 5013.32 | Q7: ($ -806.10) | R7: 4207.22 | S7: 3787.95 | T7: 85.81 % | U7: 3693.37 | V7: 73.67 % | W7: =+U7*0.03 -> 110.8011
A8: 12803 | B8: RAMIRO LEE | C8: SMP FOUR SEASONS DE MEXICO | D8: 46042 | E8: P#12803 - OC#56263 - MVR Cotizar Minicom Jack - Pin 9333. | F8: MXN | G8: 14420.32 | H8: 1 | J8: 1628.39 | K8: 1631.22 | L8: =+M8+Q8 -> 0 | M8: 0 | N8: 10624.76 | O8: =+N8*H8 -> 10624.76 | P8: 3795.56 | Q8: 0 | R8: 3795.56 | S8: 2164.34 | T8: 15.01 % | U8: 2164.34 | V8: 15.01 % | W8: =+U8*0.03 -> 64.9302
A9: 12801 | B9: ALFREDO PALOMINO | C9: ALCOM ELECTRONICOS DE MEXICO | D9: 46043 | E9: Renta de Escalera Eléctrica Por Mes ENERO 2026 | F9: MXN | G9: 10939.5 | H9: 1 | J9: 0 | K9: 0 | L9: =+M9+Q9 -> 0 | M9: 0 | N9: 10939.5 | O9: =+N9*H9 -> 10939.5 | P9: 0 | Q9: 0 | R9: 0 | S9: 0 | T9: 0.00 % | U9: 0 | V9: 0.00 % | W9: =+U9*0.03 -> 0
A10: 12794 | B10: HECTOR VELA | C10: HOFFMAN SCHROFF MANUFACTURING | D10: 46045 | E10: VENTA DE MOCHILA SWISSGEAR 5358 LAPTOP BACKPACK / VENTILADOR Y SOPORTE PARA LAPTOP LUZ LED 9" A 17" | F10: MXN | G10: 4758.78 | H10: 1 | J10: 796.57 | K10: 763.35 | L10: =+M10+Q10 -> 0 | M10: 0 | N10: 2795.04 | O10: =+N10*H10 -> 2795.04 | P10: 1963.74 | Q10: 0 | R10: 1963.74 | S10: 1200.39 | T10: 41.96 % | U10: 1167.17 | V10: 24.53 % | W10: =+U10*0.03 -> 35.0151
A11: 12787 | B11: ALFREDO PALOMINO | C11: ALCOM ELECTRONICOS DE MEXICO | D11: 46051 | E11: Cotización Diademas Plantronics C3225 | F11: MXN | G11: 2131.97 | H11: 1 | J11: 402.96 | K11: 440.71 | L11: =+M11+Q11 -> 0 | M11: 0 | N11: 1191.91 | O11: =+N11*H11 -> 1191.91 | P11: 940.06 | Q11: 0 | R11: 940.06 | S11: 499.35 | T11: 23.42 % | U11: 499.35 | V11: 23.42 % | W11: =+U11*0.03 -> 14.9805
A12: 12784 | B12: RAMIRO LEE | C12: CORNING OPTICAL COMMUNICATIONS | D12: 46051 | E12: P#12784 - PO #4501987295 #RFQReq 211514 - Pin 5086. | F12: MXN | G12: 2902.5 | H12: 1 | J12: 510.13 | K12: 555.84 | L12: =+M12+Q12 -> 0 | M12: 0 | N12: 1609.71 | O12: =+N12*H12 -> 1609.71 | P12: 1292.79 | Q12: 0 | R12: 1292.79 | S12: 736.95 | T12: 25.39 % | U12: 736.95 | V12: 25.39 % | W12: =+U12*0.03 -> 22.1085
A13: 12783 | B13: CELESTE LANDA | C13: BORGWARNER REYNOSA | D13: 46036 | E13: RFQ-S-1086: Instalación de nodo | F13: MXN | G13: 11514.7 | H13: 1 | J13: 1486.39 | K13: 1023.28 | L13: =+M13+Q13 -> 8105.84 | M13: 3033.45 | N13: 851.61 | O13: =+N13*H13 -> 851.61 | P13: 2557.25 | Q13: 5072.39 | R13: 7629.64 | S13: 6606.36 | T13: 70.28 % | U13: 6143.25 | V13: 53.35 % | W13: =+U13*0.03 -> 184.2975
A14: 12781 | B14: RAMIRO LEE | C14: CORNING OPTICAL COMMUNICATIONS | D14: 46049 | E14: P#12781 - PO 4501987914 - #RFQReq 211530 - PLANTA RCS - TIARA YANETH GUEVARA - PIN 5009. | F14: MXN | G14: 22934 | H14: 1 | J14: 2396.53 | K14: 2535.37 | L14: =+M14+Q14 -> 0 | M14: 0 | N14: 12028.25 | O14: =+N14*H14 -> 12028.25 | P14: 10905.75 | Q14: 0 | R14: 10905.75 | S14: 8370.38 | T14: 36.50 % | U14: 8370.38 | V14: 36.50 % | W14: =+U14*0.03 -> 251.1114
A15: 12776 | B15: HECTOR VELA | C15: IMPRESORA DONNECO INTERNACIONAL | D15: 46051 | E15: INSTALACION DE 11 CAMARAS EN EL AREA DE LONGFORT Y AREA GAVETAS (PLANTA 1) | F15: MXN | G15: 132514.04 | H15: 1 | J15: 17984.28 | K15: 15386.23 | L15: =+M15+Q15 -> 56740.88 | M15: 17885.37 | N15: 47437.46 | O15: =+N15*H15 -> 47437.46 | P15: 28335.7 | Q15: 38855.51 | R15: 67103.71 | S15: 51717.48 | T15: 52.60 % | U15: 49119.43 | V15: 37.07 % | W15: =+U15*0.03 -> 1473.5829
A16: 12769 | B16: HECTOR VELA | C16: IMPRESORA DONNECO INTERNACIONAL | D16: 46051 | E16: VENTA DE PROYECTO DE LA MARCA BENQ MX560C XGA 4000 (Actualizado) | F16: MXN | G16: 14153.51 | H16: 1 | J16: 1634.87 | K16: 1494.82 | L16: =+M16+Q16 -> 0 | M16: 0 | N16: 8421.68 | O16: =+N16*H16 -> 8421.68 | P16: 5731.83 | Q16: 0 | R16: 5731.83 | S16: 4237.01 | T16: 41.49 % | U16: 4096.96 | V16: 28.95 % | W16: =+U16*0.03 -> 122.9088
A17: 12759 | B17: ORLANDO MARTINEZ | C17: ALCOM ELECTRONICOS DE MEXICO | D17: 46031 | E17: Renta de Plataforma x 1 Dia Modelo 1012 | F17: MXN | G17: 3900 | H17: 1 | J17: 730 | K17: 874 | L17: =+M17+Q17 -> 0 | M17: 0 | N17: 3900 | O17: =+N17*H17 -> 3900 | P17: 0 | Q17: 0 | R17: 0 | S17: ($ -874.00) | T17: (-22.41 %) | U17: ($ -874.00) | V17: (-22.41 %) | W17: 0
A18: 12756 | B18: RAMIRO LEE | C18: AUTOMOTIVE MAQUILADORA | D18: 46030 | E18: PV#12756 - OC# - RIBBON - PIN 2180 -ALEXANDRA BRINGAS | F18: MXN | G18: 3788.24 | H18: 1 | J18: 482.29 | K18: 506.35 | L18: =+M18+Q18 -> 0 | M18: 0 | N18: 1709.04 | O18: =+N18*H18 -> 1709.04 | P18: 2079.2 | Q18: 0 | R18: 2079.2 | S18: 1572.85 | T18: 41.52 % | U18: 1572.85 | V18: 41.52 % | W18: =+U18*0.03 -> 47.1855
A19: 12751 | B19: HECTOR VELA | C19: CEBAL AMERICAS DE REYNOSA | D19: 46050 | E19: INSTALACION DE 3 NODOS DE RED (AREA DE CNC ROOM) | F19: MXN | G19: 17851.85 | H19: 1 | J19: 2171.34 | K19: 1812.69 | L19: =+M19+Q19 -> 4052.92 | M19: 2022.27 | N19: 7297.51 | O19: =+N19*H19 -> 7297.51 | P19: 6501.42 | Q19: 2030.65 | R19: 8531.08 | S19: 6718.39 | T19: 49.80 % | U19: 6359.74 | V19: 35.63 % | W19: =+U19*0.03 -> 190.7922
A20: 12735 | B20: HECTOR VELA | C20: HOFFMAN SCHROFF MANUFACTURING | D20: 46031 | E20: VENTA DE EQUIPOS (BACKPACK MOCHILA SWISSGEAR / BASE ENFRIADORA FROST EF740) | F20: MXN | G20: 9781.46 | H20: 1 | J20: 1192.08 | K20: 1032.15 | L20: =+M20+Q20 -> 0 | M20: 0 | N20: 4862.72 | O20: =+N20*H20 -> 4862.72 | P20: 4918.74 | Q20: 0 | R20: 4918.74 | S20: 3886.59 | T20: 51.92 % | U20: 3726.66 | V20: 38.10 % | W20: =+U20*0.03 -> 111.7998
A21: 12724 | B21: HECTOR VELA | C21: HOFFMAN SCHROFF MANUFACTURING | D21: 46035 | E21: VENTA DE MONTAJE DE PARED UNIVERSAL GIRATORIO / PARA MONITORES DE 75" A 110" CAPACIDAD DE 90 KGS | F21: MXN | G21: 2366.67 | H21: 1 | J21: 580.98 | K21: 575.44 | L21: =+M21+Q21 -> 0 | M21: 0 | N21: 1349.52 | O21: =+N21*H21 -> 1349.52 | P21: 1017.15 | Q21: 0 | R21: 1016.25 | S21: 440.81 | T21: 43.17 % | U21: 435.27 | V21: 18.39 % | W21: =+U21*0.03 -> 13.0581
A22: 12719 | B22: ALFREDO PALOMINO | C22: WOODCRAFTERS HOME PRODUCTS | D22: 46050 | E22: M1225-22 | SUPRESOR PARA IMPRESORAS ZT411 | F22: MXN | G22: 11810.25 | H22: 1 | J22: 1797.55 | K22: 1719.16 | L22: =+M22+Q22 -> 0 | M22: 0 | N22: 7732.44 | O22: =+N22*H22 -> 7732.44 | P22: 4077.81 | Q22: 0 | R22: 4077.81 | S22: 2358.65 | T22: 35.19 % | U22: 2280.26 | V22: 19.31 % | W22: =+U22*0.03 -> 68.4078
A23: 12714 | B23: HECTOR VELA | C23: HOFFMAN SCHROFF MANUFACTURING | D23: 46035 | E23: VENTA DE MATERIAL PARA LAPTOP / MOCHILA SWISSGEAR 5358/ BASE ENFRIADORA PARA LAPTOP_2 | F23: MXN | G23: 4891.01 | H23: 1 | J23: 688.14 | K23: 623.92 | L23: =+M23+Q23 -> 0 | M23: 0 | N23: 2491.71 | O23: =+N23*H23 -> 2491.71 | P23: 2399.3 | Q23: 0 | R23: 1697.8 | S23: 1073.88 | T23: 36.03 % | U23: 1009.66 | V23: 20.64 % | W23: =+U23*0.03 -> 30.2898
A24: 12708 | B24: ALFREDO PALOMINO | C24: WOODCRAFTERS HOME PRODUCTS | D24: 46034 | E24: Cotización M1023-19 ACTUALIZACION ATR-11 | F24: MXN | G24: 2944.5 | H24: 1 | J24: 599.7 | K24: 595.14 | L24: =+M24+Q24 -> 0 | M24: 0 | N24: 1816.5 | O24: =+N24*H24 -> 1816.5 | P24: 1128 | Q24: 0 | R24: 1126.2 | S24: 531.06 | T24: 38.40 % | U24: 526.5 | V24: 17.88 % | W24: =+U24*0.03 -> 15.795
A25: 12703 | B25: CELESTE LANDA | C25: EMERSON TOOL AND APPLIANCE COMPANY | D25: 46042 | E25: OBRA CIVIL (PESOS) | F25: MXN | G25: 57980.51 | H25: 1 | J25: 7077.39 | K25: 2169.14 | L25: =+M25+Q25 -> 4052.92 | M25: 2781.75 | N25: 8343.53 | O25: =+N25*H25 -> 8343.53 | P25: 45584.06 | Q25: 1271.17 | R25: 46855.23 | S25: 44686.09 | T25: 89.28 % | U25: 39777.84 | V25: 68.61 % | W25: =+U25*0.03 -> 1193.3352
A26: 12682 | B26: HECTOR VELA | C26: NEWOPTIX RS | D26: 46045 | E26: SUMINISTRO E INSTALACION DE CONTROL DE ACCESO PARA 9 PUERTAS (AREA DE OFICINAS Y PASILLO DE PRIMERA PISO + OFICINAS DE 2do PISO) LECTORA + BOTON (NO INCLUYE EQUIPO DE COMPUTO) | F26: MXN | G26: 306878.08 | H26: 1 | J26: 34368.91 | K26: 42341 | L26: =+M26+Q26 -> 101521.32 | M26: 50838.01 | N26: 174539.69 | O26: =+N26*H26 -> 174539.69 | P26: 30817.07 | Q26: 50683.31 | R26: 81409.06 | S26: 39068.06 | T26: 12.73 % | U26: 39068.06 | V26: 12.73 % | W26: 0
A27: 12645 | B27: HECTOR VELA | C27: HOFFMAN SCHROFF MANUFACTURING | D27: 46031 | E27: VENTA DE MATERIAL PARA LAPTOP / MOCHILA SWISSGEAR 5358/ BASE ENFRIADORA PARA LAPTOP | F27: MXN | G27: 4891.01 | H27: 1 | J27: 688.14 | K27: 623.92 | L27: =+M27+Q27 -> 0 | M27: 0 | N27: 2491.71 | O27: =+N27*H27 -> 2491.71 | P27: 2399.3 | Q27: 0 | R27: 1697.8 | S27: 1073.88 | T27: 36.03 % | U27: 1009.66 | V27: 20.64 % | W27: =+U27*0.03 -> 30.2898
A28: 12563 | B28: RAMIRO LEE | C28: CORNING OPTICAL COMMUNICATIONS | D28: 46028 | E28: P#12563 - PO 4501974932 - #RFQReq:206611 - PDU´S - PIN 3060. | F28: MXN | G28: 263310.36 | H28: 1 | J28: 17956.23 | K28: 23406.95 | L28: =+M28+Q28 -> 0 | M28: 0 | N28: 121878.66 | O28: =+N28*H28 -> 121878.66 | P28: 141431.7 | Q28: 0 | R28: 140588.14 | S28: 117181.19 | T28: 44.50 % | U28: 117181.19 | V28: 44.50 % | W28: =+U28*0.03 -> 3515.4357
A29: 12426 | B29: ALFREDO PALOMINO | C29: ALCOM ELECTRONICOS DE MEXICO | D29: 46052 | E29: Cotizar Requerimiento en Porton de Accesso Vehicular | F29: MXN | G29: 238150.37 | H29: 1 | J29: 28625.93 | K29: 25569.96 | L29: =+M29+Q29 -> 56950.61 | M29: 33592.88 | N29: 114159 | O29: =+N29*H29 -> 114159 | P29: 67040.76 | Q29: 23357.73 | R29: 89159.71 | S29: 63589.75 | T29: 38.72 % | U29: 60533.78 | V29: 25.42 % | W29: =+U29*0.03 -> 1816.0134
A30: 12372 | B30: RAMIRO LEE | C30: CORNING OPTICAL COMMUNICATIONS | D30: 46052 | E30: PV#12372 - PO # 4501933175 - #RFQReq 197376 - Provisión de Personal Técnico Para Actividades de Instalación de Nodos de Red - (octubre) - PIN 2219 | F30: MXN | G30: 925190.62 | H30: 1 | J30: 91420.12 | K30: 113979.94 | L30: =+M30+Q30 -> 873241.9 | M30: 138019.23 | N30: 373530.65 | O30: =+N30*H30 -> 373530.65 | P30: ($ -321,581.93) | Q30: 735222.67 | R30: 413640.74 | S30: 299660.8 | T30: 32.39 % | U30: 299660.8 | V30: 32.39 % | W30: =+U30*0.03 -> 8989.824
A31: 12321 | B31: CELESTE LANDA | C31: BCS-AIS ENSAMBLES MEXICO | D31: 46038 | E31: CONTROL DE ACCESO ALMACEN | F31: MXN | G31: 6143.36 | H31: 1 | J31: 905.3 | K31: 250 | L31: =+M31+Q31 -> 0 | M31: 0 | N31: 0 | O31: =+N31*H31 -> 0 | P31: 6143.36 | Q31: 0 | R31: 6143.36 | S31: 5893.36 | T31: 110.67 % | U31: 5238.06 | V31: 85.26 % | W31: =+U31*0.03 -> 157.1418
A32: 12314 | B32: ALFREDO PALOMINO | C32: IIMED MEDICAL SOLUTIONS LLC | D32: 46027 | E32: VENTA E INSTALACION DE 8 DISCOS DUROS DE 10 TB | F32: USD | G32: 5403.91 | H32: 18.48 | I32: =+G32*H32 -> 99864.257 | J32: 462.29 | K32: 454.46 | L32: =+M32+Q32 -> 930.95 | M32: 66.73 | N32: 2668.24 | O32: =+N32*H32 -> 49309.075 | P32: 1804.72 | Q32: 864.22 | R32: 2668.94 | S32: 2214.48 | T32: 49.53 % | U32: 2206.65 | V32: 40.83 % | W32: =+U32*0.03 -> 66.1995
A33: 12308 | B33: ALFREDO PALOMINO | C33: ALCOM ELECTRONICOS DE MEXICO | D33: 46027 | E33: LICENCIAS PARA 6 CONTROL DE ACCESO Y 7 CAMARAS MD3 | F33: MXN | G33: 10342.93 | H33: 1 | J33: 1522.97 | K33: 1413.84 | L33: =+M33+Q33 -> 0 | M33: 0 | N33: 7274.01 | O33: =+N33*H33 -> 7274.01 | P33: 3068.92 | Q33: 0 | R33: 3068.92 | S33: 1655.08 | T33: 30.73 % | U33: 1545.95 | V33: 14.95 % | W33: =+U33*0.03 -> 46.3785
A34: 12240 | B34: ALFREDO PALOMINO | C34: IIMED MEDICAL SOLUTIONS LLC | D34: 46034 | E34: INSTALACION DE 14 CAMARAS VIVOTEK PLANTA 1 | F34: USD | G34: 15877.57 | H34: 18.64 | I34: =+G34*H34 -> 295957.9 | J34: 1456.05 | K34: 1387.82 | L34: =+M34+Q34 -> 3472.67 | M34: 1514.6 | N34: 6594.65 | O34: =+N34*H34 -> 122924.28 | P34: 5810.25 | Q34: 1958.07 | R34: 7684.76 | S34: 6296.94 | T34: 48.83 % | U34: 6228.71 | V34: 39.23 % | W34: =+U34*0.03 -> 186.8613
A35: 11988 | B35: HECTOR VELA | C35: SANMINA-SCI DE MEXICO | D35: 46036 | E35: SUMINSITRO E INSTALACION DE (RELOJ MAESTRO + CONFIGURACION) Actualizado | F35: MXN | G35: 48725.74 | H35: 1 | J35: 6407.08 | K35: 6533.67 | L35: =+M35+Q35 -> 24867.36 | M35: 12818.24 | N35: 17126.09 | O35: =+N35*H35 -> 17126.09 | P35: 6732.29 | Q35: 12049.12 | R35: 18780.31 | S35: 12246.64 | T35: 25.13 % | U35: 12246.64 | V35: 25.13 % | W35: =+U35*0.03 -> 367.3992
A36: 11612 | B36: RAMIRO LEE | C36: CORNING MONTERREY | D36: 46049 | E36: P#11612 - PO #4501900672 -RFQReq:188794 Instalación de servicio de 40 cableados área C&A para instalación de máquinas Pin 8069 | F36: MXN | G36: 522366.4 | H36: 1 | J36: 38114.2 | K36: 19355.71 | L36: =+M36+Q36 -> 69678.42 | M36: 12765.81 | N36: 87058.13 | O36: =+N36*H36 -> 87058.13 | P36: 365629.85 | Q36: 56912.61 | R36: 422390.93 | S36: 403035.22 | T36: 84.45 % | U36: 384276.73 | V36: 73.56 % | W36: =+U36*0.03 -> 11528.302
L37: =SUBTOTAL(9,L2:L36) -> 4403.62 | O37: =SUM(O2:O36) -> 1216313.6 | P37: =SUBTOTAL(9,P2:P36) -> 7614.97 | V37: MXN | W37: 31241.109
V38: USD | W38: 253.0608
C39: 17.6768 | D39: MX | E39: USD | G39: =SUBTOTAL(9,G2:G38) -> 21281.48 | I39: =SUBTOTAL(9,I32:I38) -> 395822.16 | N39: =SUBTOTAL(9,N2:N38) -> 9262.89 | Q39: mxn | R39: =SUBTOTAL(9,R2:R38) -> 10353.7 | T39: mxn | U39: 1080438.4 | W39: =+W37+W38*17.2532 -> 35607.218
C40: MO COB | D40: 1235140.9 | E40: 4403.62 | N40: 1044080.2 | Q40: usd | R40: 10353.7 | T40: usd | U40: =8435.36 -> 8435.36
C41: MAT UTILIDAD | D41: 763081.54 | E41: 7614.97 | N41: 9262.89 | Q41: mxn | R41: =+R39+R40*17.5 -> 191543.45 | T41: mxn | U41: =+U39+U40*17.5 -> 1228057.2
D42: =+D41+D40 -> 1998222.4 | E42: =+(E40+E41)*C39 -> 212450.21 | N42: =+N40+N41*C39 -> 1207818.5 | Q42: gasto | R42: =+D44 -> 1660050.3 | T42: gasto | U42: =+D44 -> 1660050.3
C43: TOTAL | D43: =+D42+E42 -> 2210672.7 | Q43: utilidad | R43: =+R41-R42 -> -1468506.9 | T43: utilidad | U43: =+U41-U42 -> -431993.17
C44: GASTO OP. | D44: 1660050.3 | N44: =+#REF!+#REF!+#REF!-'ENERO '!N45 -> #REF!
C45: UTILIDAD PROY | D45: =+D43-D44 -> 550622.32 | N45: =+N42+FEBRERO!N43+MARZO!N46 -> 3832643.5

Sheet FEBRERO
A1: Id | B1: Promotor | C1: Cliente | D1: Fecha | E1: Descripcion | F1: Moneda | G1: Cotizado cliente | H1: TC | J1: Indirecto presupuestado | K1: Indirecto Real | L1: MO COBRADA | M1: Mano obra real | N1: Material real | P1: Material utilidad | Q1: Mano obra utilidad | R1: Utilidad | S1: Utilidad despuﾃｩs de indirectos | T1: % Utilidad antes de indirectos | U1: $ Utilidad a comision | V1: % Utilidad a comision | W1: % Utilidad promedio
A2: 13021 | B2: ALFREDO PALOMINO | C2: MADRAX GREEN AUTOMATION | D2: 46080 | E2: COTIZACION MATERIAL | F2: MXN | G2: 3157.87 | H2: 1 | J2: 565.79 | K2: 699.69 | L2: =+M2+Q2 -> 0 | M2: 0 | N2: 2810.5 | O2: =+N2*H2 -> 2810.5 | P2: 347.37 | Q2: 0 | R2: 347.37 | S2: ($ -352.32) | T2: (-11.16 %) | U2: ($ -352.32) | V2: (-11.16 %) | W2: 0.6
A3: 13018 | B3: ALFREDO PALOMINO | C3: ALCOM ELECTRONICOS DE MEXICO | D3: 46080 | E3: INSTALACION DE DOS CAMARAS | F3: MXN | G3: 15116.36 | H3: 1 | J3: 2034.53 | K3: 1507.4 | L3: =+M3+Q3 -> 4220.58 | M3: 2025.62 | N3: 5200.17 | O3: =+N3*H3 -> 5200.17 | P3: 5695.61 | Q3: 2194.96 | R3: 7888.85 | S3: 6381.45 | T3: 0.5567 | U3: 5854.32 | V3: 0.3873 | W3: 0.3
A4: 13003 | B4: CELESTE LANDA | C4: E&M INDUSTRIAL SUPPLIES | D4: 46080 | E4: DIAGNOSTICO DE RED | F4: MXN | G4: 4399.98 | H4: 1 | J4: 640 | K4: 525.58 | L4: =+M4+Q4 -> 4399.98 | M4: 1413.23 | N4: 0 | O4: =+N4*H4 -> 0 | P4: 0 | Q4: 2986.75 | R4: 2986.75 | S4: 2461.17 | T4: 0.7048 | U4: 2346.75 | V4: 0.5334 | W4: 0
A5: 12977 | B5: ALFREDO PALOMINO | C5: ALCOM ELECTRONICOS DE MEXICO | D5: 46080 | E5: Cotizar baterﾃｭa para Laptop Dell LATITUDE 3420 | F5: MXN | G5: 3600 | H5: 1 | J5: 610 | K5: 413.82 | L5: =+M5+Q5 -> 0 | M5: 0 | N5: 1023.84 | O5: =+N5*H5 -> 1023.84 | P5: 2576.16 | Q5: 0 | R5: 2447.16 | S5: 2033.34 | T5: 0.7343 | U5: 1837.16 | V5: 0.5103 | W5: 0.6
A6: 12974 | B6: RAMIRO LEE | C6: AUTOMOTIVE MAQUILADORA | D6: 46078 | E6: PV#12974 - OC#62035 - PIN 6440 -ALEXANDRA BRINGAS | F6: MXN | G6: 3788.24 | H6: 1 | J6: 732.29 | K6: 725.74 | L6: =+M6+Q6 -> 0 | M6: 0 | N6: 1504.9 | O6: =+N6*H6 -> 1504.9 | P6: 2283.34 | Q6: 0 | R6: 2149.03 | S6: 1423.29 | T6: 0.569 | U6: 1416.74 | V6: 0.374 | W6: 0
A7: 12964 | B7: ALFREDO PALOMINO | C7: ALCOM ELECTRONICOS DE MEXICO | D7: 46076 | E7: Renta de Escalera Elﾃｩctrica Por Mes FEBRERO 2026 | F7: MXN | G7: 10939.5 | H7: 1 | J7: 0 | K7: 0 | L7: =+M7+Q7 -> 0 | M7: 0 | N7: 10939.5 | O7: =+N7*H7 -> 10939.5 | P7: 0 | Q7: 0 | R7: 0 | S7: 0 | T7: 0 | U7: 0 | V7: 0 | W7: 0.1
A8: 12947 | B8: ALFREDO PALOMINO | C8: ALPS ALPINE NORTH AMERICA | D8: 46077 | E8: Solicitud de cotizaciﾃｳn Lainas | F8: USD | G8: 415.95 | H8: 17.23 | I8: =+G8*H8 -> 7166.8185 | J8: 54.84 | K8: 48.97 | L8: =+M8+Q8 -> 0 | M8: 0 | N8: 215.37 | O8: =+N8*H8 -> 3710.8251 | P8: 200.58 | Q8: 0 | R8: 159.66 | S8: 110.69 | T8: 0.398 | U8: 104.82 | V8: 0.252 | W8: 0.65
A9: 12941 | B9: HECTOR VELA | C9: CARPLASTIC | D9: 46072 | E9: VENTA DE TARJETAS DE CONTROL DE ACCESO 200PGGMN HID (actualizado a 100 pzas) | F9: MXN | G9: 14513 | H9: 1 | J9: 1548.19 | K9: 1290.27 | L9: =+M9+Q9 -> 0 | M9: 0 | N9: 6079 | O9: =+N9*H9 -> 6079 | P9: 8434 | Q9: 0 | R9: 8434 | S9: 7143.73 | T9: 0.5989 | U9: 6885.81 | V9: 0.4745 | W9: 0.8
A10: 12939 | B10: HECTOR VELA | C10: HOFFMAN SCHROFF MANUFACTURING | D10: 46072 | E10: VENTA DE TECLADO + MOUSE INALAMBRICO DELL KM3322W_5 PZAS | F10: MXN | G10: 7167.35 | H10: 1 | J10: 889.86 | K10: 830.82 | L10: =+M10+Q10 -> 0 | M10: 0 | N10: 2544.75 | O10: =+N10*H10 -> 2544.75 | P10: 4622.6 | Q10: 0 | R10: 4622.6 | S10: 3791.78 | T10: 0.6532 | U10: 3732.74 | V10: 0.5208 | W10: 0
A11: 12923 | B11: ORLANDO MARTINEZ | C11: ALCOM ELECTRONICOS DE MEXICO | D11: 46070 | E11: Renta de montacargas 2.5 Ton | F11: MXN | G11: 12000 | H11: 1 | J11: 1162 | K11: 2181.52 | L11: =+M11+Q11 -> 0 | M11: 0 | N11: 12072 | O11: =+N11*H11 -> 12072 | P11: ($ -72.00) | Q11: 0 | R11: ($ -72.00) | S11: ($ -2,253.52) | T11: (-18.78 %) | U11: ($ -2,253.52) | V11: (-18.78 %) | W11: 0
A12: 12921 | B12: CELESTE LANDA | C12: MIKUNI AMERICAN CORPORATION | D12: 46070 | E12: MRORC25-2199_M.M | F12: USD | G12: 734.08 | H12: 17.24 | I12: =+G12*H12 -> 12655.539 | J12: 90.29 | K12: 101.44 | L12: =+M12+Q12 -> 0 | M12: 0 | N12: 543.26 | O12: =+N12*H12 -> 9365.8024 | P12: 190.82 | Q12: 0 | R12: 190.82 | S12: 89.38 | T12: 0.1218 | U12: 89.38 | V12: 0.1218 | W12: 0.55
A13: 12919 | B13: ALFREDO PALOMINO | C13: ALCOM ELECTRONICOS DE MEXICO | D13: 46077 | E13: COTIZACION DE BATERIA LENOVO T460s | F13: MXN | G13: 2984 | H13: 1 | J13: 548.4 | K13: 557.85 | L13: =+M13+Q13 -> 0 | M13: 0 | N13: 1924.06 | O13: =+N13*H13 -> 1924.06 | P13: 1059.94 | Q13: 0 | R13: 1059.94 | S13: 502.09 | T13: 0.1683 | U13: 502.09 | V13: 0.1683 | W13: 0.6
A14: 12912 | B14: CELESTE LANDA | C14: E&M INDUSTRIAL SUPPLIES | D14: 46062 | E14: MIGRACION DE IVMS A PC | F14: MXN | G14: 3999.98 | H14: 1 | J14: 670 | K14: 398.39 | L14: =+M14+Q14 -> 3999.98 | M14: 706.62 | N14: 0 | O14: =+N14*H14 -> 0 | P14: 0 | Q14: 3293.36 | R14: 3293.36 | S14: 2894.97 | T14: 0.8912 | U14: 2623.36 | V14: 0.6558 | W14: 0
A15: 12902 | B15: RAMIRO LEE | C15: CORNING OPTICAL COMMUNICATIONS | D15: 46080 | E15: P#12902 - PO 4501997300 - #RFQReq 213569 - SHEYLA AGUILAR Ext:701 - PLANTA RYDN - #1 | F15: MXN | G15: 8680.48 | H15: 1 | J15: 1035.38 | K15: 966.98 | L15: =+M15+Q15 -> 0 | M15: 0 | N15: 3773.55 | O15: =+N15*H15 -> 3773.55 | P15: 4906.93 | Q15: 0 | R15: 4906.93 | S15: 3939.95 | T15: 0.5732 | U15: 3871.55 | V15: 0.446 | W15: 0
A16: 12898 | B16: RAMIRO LEE | C16: CORNING OPTICAL COMMUNICATIONS | D16: 46080 | E16: PV#12898 - PO # 4501933175 - #RFQReq 197376 - Provisiﾃｳn de Personal Tﾃｩcnico Para Actividades de Instalaciﾃｳn de Nodos de Red - (Febrero) - PIN 7799. | F16: MXN | G16: 925190.62 | H16: 1 | J16: 91420.12 | K16: 108761.74 | L16: =+M16+Q16 -> 873241.9 | M16: 124356.59 | N16: 361998.42 | O16: =+N16*H16 -> 361998.42 | P16: ($ -310,049.70) | Q16: 748885.31 | R16: 438835.61 | S16: 330073.87 | T16: 0.3568 | U16: 330073.87 | V16: 0.3568 | W16: 0.07
A17: 12897 | B17: RAMIRO LEE | C17: FILTERTEK DE MEXICO | D17: 46058 | E17: P#12897 - PO 480R7252 - Cotizaciﾃｳn cable HDMI - Pin 4704. | F17: MXN | G17: 1097.6 | H17: 1 | J17: 321.71 | K17: 321.71 | L17: =+M17+Q17 -> 0 | M17: 0 | N17: 551.56 | O17: =+N17*H17 -> 551.56 | P17: 546.04 | Q17: 0 | R17: 546.04 | S17: 224.33 | T17: 0.4975 | U17: 224.33 | V17: 0.2044 | W17: 0.99
A18: 12889 | B18: RAMIRO LEE | C18: AUTOMOTIVE MAQUILADORA | D18: 46078 | E18: P#12889 - OC# #61849 - Instalaciﾃｳn de una segunda conexiﾃｳn HDMI, con integraciﾃｳn de caja de conexiones en la mesa de la Sala de Reuniones de la Planta 7 Caliper, Terre Power, para habilitar la proyecciﾃｳn en TV. Pin 9885. | F18: MXN | G18: 19243.02 | H18: 1 | J18: 3420.54 | K18: 2264.81 | L18: =+M18+Q18 -> 12519.81 | M18: 2027.23 | N18: 2711.71 | O18: =+N18*H18 -> 2711.71 | P18: 4011.5 | Q18: 10492.58 | R18: 14502.36 | S18: 12237.55 | T18: 0.8137 | U18: 11081.82 | V18: 0.5759 | W18: 0.36
A19: 12882 | B19: RAMIRO LEE | C19: FILTERTEK DE MEXICO | D19: 46064 | E19: P#12882 - PO 480R7248 - Cotizacion chapa de seguridad - Pin 8199. | F19: MXN | G19: 5737.54 | H19: 1 | J19: 743.96 | K19: 655.47 | L19: =+M19+Q19 -> 0 | M19: 0 | N19: 3118.96 | O19: =+N19*H19 -> 3118.96 | P19: 2618.58 | Q19: 0 | R19: 2477.2 | S19: 1821.73 | T19: 0.4472 | U19: 1733.24 | V19: 0.3021 | W19: 0.51
A20: 12881 | B20: RAMIRO LEE | C20: CORNING OPTICAL COMMUNICATIONS | D20: 46076 | E20: P#12881 - PO 4501993451 #RFQReq:213439 -Filtros - Pin 4020. | F20: MXN | G20: 5598.8 | H20: 1 | J20: 733.53 | K20: 660.25 | L20: =+M20+Q20 -> 0 | M20: 0 | N20: 2159.17 | O20: =+N20*H20 -> 2159.17 | P20: 3439.63 | Q20: 0 | R20: 2508.26 | S20: 1848.01 | T20: 0.4611 | U20: 1774.73 | V20: 0.317 | W20: 0
A21: 12877 | B21: RAMIRO LEE | C21: CORNING OPTICAL COMMUNICATIONS | D21: 46062 | E21: P#12877 - PO 4501991572 #RFQReq:212669 - RENTA DE 1 MESES POR 1 PLATAFORMA EN RAM - ENERO - PIN 6239. | F21: MXN | G21: 19710 | H21: 1 | J21: 2917.6 | K21: 4391.86 | L21: =+M21+Q21 -> 0 | M21: 0 | N21: 21799.26 | O21: =+N21*H21 -> 21799.26 | P21: ($ -2,089.26) | Q21: 0 | R21: ($ -2,089.26) | S21: ($ -6,481.12) | T21: (-32.88 %) | U21: ($ -6,481.12) | V21: (-32.88 %) | W21: 0.4
A22: 12855 | B22: HECTOR VELA | C22: LANDIS & GYR | D22: 46070 | E22: SERVICIO E INSTALACION DE 6 NODOS DE RED (5 NODOS AREA DE OFICINAS PLANTA 1 + 1 NODO AREA DE OFICINAS PLANTA 2) RETIRO DE CABLEADO DE LAS ISLAS DE PLANTA | F22: MXN | G22: 16815.47 | H22: 1 | J22: 1985.25 | K22: 1394.39 | L22: =+M22+Q22 -> 9251.35 | M22: 2138.56 | N22: 3918.79 | O22: =+N22*H22 -> 3918.79 | P22: 3645.33 | Q22: 7112.79 | R22: 10758.12 | S22: 9363.73 | T22: 0.6749 | U22: 8772.87 | V22: 0.5217 | W22: 0.35
A23: 12845 | B23: ALFREDO PALOMINO | C23: ALCOM ELECTRONICOS DE MEXICO | D23: 46058 | E23: Cotizacion - Bateria URGENTE | F23: MXN | G23: 2278 | H23: 1 | J23: 228.53 | K23: 217.45 | L23: =+M23+Q23 -> 0 | M23: 0 | N23: 1270.77 | O23: =+N23*H23 -> 1270.77 | P23: 1007.23 | Q23: 0 | R23: 1007.23 | S23: 789.78 | T23: 0.447 | U23: 778.7 | V23: 0.3418 | W23: 0.7
A24: 12838 | B24: ALFREDO PALOMINO | C24: ALPS ALPINE NORTH AMERICA | D24: 46079 | E24: Cotizaciﾃｳn adaptador Convertidor DB9 Macho RS232 a USB | F24: USD | G24: 231.34 | H24: 17.69 | I24: =+G24*H24 -> 4092.4046 | J24: 34.7 | K24: 39.14 | L24: =+M24+Q24 -> 0 | M24: 0 | N24: 156.34 | O24: =+N24*H24 -> 2765.6546 | P24: 75 | Q24: 0 | R24: 67.42 | S24: 28.28 | T24: 0.1222 | U24: 28.28 | V24: 0.1222 | W24: 0.8
A25: 12835 | B25: CELESTE LANDA | C25: BCS-AIS ENSAMBLES MEXICO | D25: 46076 | E25: INSTALACION DE 22 SERVICOS DE RED EN BODEGA Y REUBICACION DE APS | F25: MXN | G25: 100677.17 | H25: 1 | J25: 10301.87 | K25: 8863.87 | L25: =+M25+Q25 -> 35356.94 | M25: 7646.75 | N25: 43800.35 | O25: =+N25*H25 -> 43800.35 | P25: 21519.88 | Q25: 27710.19 | R25: 49230.07 | S25: 40366.2 | T25: 0.5033 | U25: 38928.2 | V25: 0.3867 | W25: 0.6
A26: 12829 | B26: RAMIRO LEE | C26: CORNING OPTICAL COMMUNICATIONS | D26: 46072 | E26: P#12829 - PO 4501988726 - RFQReq 207415 - PLANTA: RYAI - LLULIANA FRANCO - PIN 2844 | F26: MXN | G26: 829.59 | H26: 1 | J26: 288.92 | K26: 337.7 | L26: =+M26+Q26 -> 0 | M26: 0 | N26: 461.55 | O26: =+N26*H26 -> 461.55 | P26: 368.04 | Q26: 0 | R26: 191.5 | S26: ($ -146.20) | T26: (-17.62 %) | U26: ($ -146.20) | V26: (-17.62 %) | W26: 0
A27: 12810 | B27: ALFREDO PALOMINO | C27: ALCOM ELECTRONICOS DE MEXICO | D27: 46072 | E27: REPARACION PANTALLA | F27: MXN | G27: 3600 | H27: 1 | J27: 610 | K27: 663.06 | L27: =+M27+Q27 -> 0 | M27: 0 | N27: 2581.6 | O27: =+N27*H27 -> 2581.6 | P27: 1018.4 | Q27: 0 | R27: 1018.4 | S27: 355.34 | T27: 0.0987 | U27: 355.34 | V27: 0.0987 | W27: 0.6
A28: 12802 | B28: RAMIRO LEE | C28: CORNING OPTICAL COMMUNICATIONS | D28: 46080 | E28: P#12881 - PO 4501993451 #RFQReq:213439 -Filtros - Planta RCS - Pin 4020. | F28: MXN | G28: 1922.7 | H28: 1 | J28: 393.26 | K28: 403.08 | L28: =+M28+Q28 -> 0 | M28: 0 | N28: 805.7 | O28: =+N28*H28 -> 805.7 | P28: 1117 | Q28: 0 | R28: 1117 | S28: 713.92 | T28: 0.3713 | U28: 713.92 | V28: 0.3713 | W28: 0
A29: 12760 | B29: HECTOR VELA | C29: INDO-MIM MEXICO | D29: 46072 | E29: VENTA DE MATERIAL DE RED (PINZAS RJ45, BOBINS DE CABLE, PLUG RJ45, JACK, FACE PLATE ) | F29: MXN | G29: 21480.47 | H29: 1 | J29: 2423.55 | K29: 2253.63 | L29: =+M29+Q29 -> 0 | M29: 0 | N29: 14258.66 | O29: =+N29*H29 -> 14258.66 | P29: 7221.81 | Q29: 0 | R29: 7221.72 | S29: 4968.09 | T29: 0.3441 | U29: 4798.17 | V29: 0.2234 | W29: 0.38
A30: 12753 | B30: ALFREDO PALOMINO | C30: IIMED MEDICAL SOLUTIONS LLC | D30: 46062 | E30: QUOTE RECORDER OPERATING SYSTEM FAILURE | F30: USD | G30: 444.96 | H30: 17.98 | I30: =+G30*H30 -> 8000.3808 | J30: 60.62 | K30: 33.41 | L30: =+M30+Q30 -> 444.96 | M30: 69.16 | N30: 31.15 | O30: =+N30*H30 -> 560.077 | P30: ($ -31.15) | Q30: 375.8 | R30: 344.65 | S30: 311.24 | T30: 0.8357 | U30: 284.03 | V30: 0.6383 | W30: 0
A31: 12712 | B31: RAMIRO LEE | C31: CORNING OPTICAL COMMUNICATIONS | D31: 46057 | E31: P#12712 - PO PENDIENTE - #RFQReq:209832 - RENTA DE 1 MESES POR 1 PLATAFORMA EN RAM - DICIEMBRE. - PIN 2615. | F31: MXN | G31: 19710 | H31: 1 | J31: 2917.6 | K31: 4391.86 | L31: =+M31+Q31 -> 0 | M31: 0 | N31: 21799.26 | O31: =+N31*H31 -> 21799.26 | P31: ($ -2,089.26) | Q31: 0 | R31: ($ -2,089.26) | S31: ($ -6,481.12) | T31: (-32.88 %) | U31: ($ -6,481.12) | V31: (-32.88 %) | W31: 0.4
A32: 12710 | B32: HECTOR VELA | C32: CEBAL AMERICAS DE REYNOSA | D32: 46076 | E32: REVISION DE SISTEMA DE VOCEO Y CABLEADO | F32: MXN | G32: 37110.3 | H32: 1 | J32: 6956.88 | K32: 5746.32 | L32: =+M32+Q32 -> 24211.64 | M32: 2028.3 | N32: 14470.88 | O32: =+N32*H32 -> 14470.88 | P32: ($ -1,572.22) | Q32: 22183.34 | R32: 20610.95 | S32: 14864.63 | T32: 0.588 | U32: 13654.07 | V32: 0.3679 | W32: 0.35
A33: 12704 | B33: CELESTE LANDA | C33: E&M INDUSTRIAL SUPPLIES | D33: 46078 | E33: CANALIZACION HERNAN ESPINOZA | F33: MXN | G33: 35074.86 | H33: 1 | J33: 4425.33 | K33: 4303.48 | L33: =+M33+Q33 -> 18238.14 | M33: 10358.2 | N33: 11739.05 | O33: =+N33*H33 -> 11739.05 | P33: 5097.67 | Q33: 7879.94 | R33: 12977.61 | S33: 8674.13 | T33: 0.3735 | U33: 8552.28 | V33: 0.2438 | W33: 0.35
A34: 12535 | B34: ALFREDO PALOMINO | C34: ALCOM ELECTRONICOS DE MEXICO | D34: 46058 | E34: VENTA E INSTALACION DE MANTAS DE PROYECCION ELECTRICAS | F34: MXN | G34: 54551.76 | H34: 1 | J34: 5798.72 | K34: 5070.36 | L34: =+M34+Q34 -> 12248.46 | M34: 6711.46 | N34: 21318.46 | O34: =+N34*H34 -> 21318.46 | P34: 20984.84 | Q34: 5537 | R34: 23398.11 | S34: 18327.75 | T34: 0.4423 | U34: 17599.39 | V34: 0.3226 | W34: 0.6
A35: 12433 | B35: CELESTE LANDA | C35: BORGWARNER REYNOSA | D35: 46065 | E35: RFQ-P-3144 | F35: MXN | G35: 9232.98 | H35: 1 | J35: 1234.85 | K35: 1022.69 | L35: =+M35+Q35 -> 0 | M35: 0 | N35: 4829.31 | O35: =+N35*H35 -> 4829.31 | P35: 4403.67 | Q35: 0 | R35: 4403.67 | S35: 3380.98 | T35: 0.4999 | U35: 3168.82 | V35: 0.3432 | W35: 0.5
A36: 12332 | B36: ALFREDO PALOMINO | C36: ALCOM ELECTRONICOS DE MEXICO | D36: 46078 | E36: GARANTIA P-10179 | F36: MXN | G36: 0.62 | H36: 1 | J36: 250.09 | K36: 2031.31 | L36: 0 | M36: 1162.95 | N36: 9606.88 | O36: =+N36*H36 -> 9606.88 | P36: ($ -9,606.26) | Q36: ($ -1,162.95) | R36: ($ -11,109.99) | S36: ($ -13,141.30) | T36: (-2,119,564.52 %) | U36: ($ -13,141.30) | V36: (-2,119,564.52 %) | W36: 0.2
A37: 12115 | B37: CELESTE LANDA | C37: BCS-AIS ENSAMBLES MEXICO | D37: 46078 | E37: MOVIMIENTO NUEVA BODEGA | F37: MXN | G37: 276992.94 | H37: 1 | J37: 27245.68 | K37: 32840.47 | L37: =+M37+Q37 -> 112332.19 | M37: 61500.33 | N37: 122971.21 | O37: =+N37*H37 -> 122971.21 | P37: 41689.54 | Q37: 50831.86 | R37: 92518.41 | S37: 59677.94 | T37: 0.2154 | U37: 59677.94 | V37: 0.2154 | W37: 0.6
A38: 12001 | B38: RAMIRO LEE | C38: CORNING OPTICAL COMMUNICATIONS | D38: 46078 | E38: P#12001 - PO #4501930250 - #RFQReq:195541 Instalaciﾃｳn de 25 nodos de red planta Aneex. - Pin 7368. | F38: MXN | G38: 20264.84 | H38: 1 | J38: 2770.92 | K38: 5236.85 | L38: =+M38+Q38 -> 18827.64 | M38: 16739.07 | N38: 2470.89 | O38: =+N38*H38 -> 2470.89 | P38: ($ -1,033.69) | Q38: 2088.57 | R38: 1053.93 | S38: ($ -4,182.92) | T38: (-20.64 %) | U38: ($ -4,182.92) | V38: (-20.64 %) | W38: 0
A39: 11742 | B39: CELESTE LANDA | C39: EMERSON TOOL AND APPLIANCE COMPANY | D39: 46078 | E39: CAMARAS ESTACIONAMIENTO (DOLARES) | F39: USD | G39: 37813.55 | H39: 19.57 | I39: =+G39*H39 -> 740011.17 | J39: 2280.55 | K39: 1829.79 | L39: =+M39+Q39 -> 4891.52 | M39: 2021.78 | N39: 19427.38 | O39: =+N39*H39 -> 380193.83 | P39: 13494.65 | Q39: 2869.74 | R39: 16315.02 | S39: 14485.23 | T39: 0.4434 | U39: 14034.47 | V39: 0.3711 | W39: 0.36
H40: ALFREDO | I40: 19259.604 | L40: =SUBTOTAL(9,L2:L39) -> 444.96 | N40: =SUBTOTAL(9,N2:N39) -> 402.86 | O40: =SUM(O2:O39) -> 1113110.9 | P40: =SUBTOTAL(9,P2:P39) -> 275.58
H41: CELESTE | I41: 752666.71 | N41: 716514.71
C42: 17.2286 | D42: MX | E42: USD | N42: 20373.5
C43: MO COB | D43: 1128848.6 | E43: 5336.48 | N43: =+N41+N42*C42 -> 1067521.6
C44: MAT UTILIDAD | D44: 148615.11 | E44: 13961.05
D45: =+D44+D43 -> 1277463.7 | E45: =+(E43+E44)*C42 -> 332469.43
C46: TOTAL | D46: =+D45+E45 -> 1609933.1
C47: GASTO OP. | D47: 1259904
C48: UTILIDAD PROY | D48: =+D46-D47 -> 350029.1

Sheet MARZO
A1: Id | B1: Promotor | C1: Cliente | D1: Fecha | E1: Descripcion | F1: Moneda | G1: Cotizado cliente | H1: TC | J1: Indirecto presupuestado | K1: Indirecto Real | L1: MO COBRADA | M1: Mano obra real | N1: Material real | P1: Material utilidad | Q1: Mano obra utilidad | R1: Utilidad | S1: Utilidad despuÃ©s de indirectos | T1: % Utilidad antes de indirectos | U1: $ Utilidad a comision | V1: % Utilidad a comision | W1: % Utilidad promedio
A2: 13127 | B2: ORLANDO MARTINEZ | C2: ALCOM ELECTRONICOS DE MEXICO | D2: 46106 | E2: REPARACION DE CELULAR | F2: MXN | G2: 4633.02 | H2: 1 | J2: 744.19 | K2: 616.57 | L2: =+M2+Q2 -> 0 | M2: 0 | N2: 2291.1 | O2: =+N2*H2 -> 2291.1 | P2: 2341.92 | Q2: 0 | R2: 2341.92 | S2: 1725.35 | T2: 0.533 | U2: 1597.73 | V2: 0.3449 | W2: 0.5
A3: 13126 | B3: RAMIRO LEE | C3: CORNING MONTERREY | D3: 46112 | E3: #13126 - PO 4502010682 - #RFQReq 217694 - InstalaciÃ³n de servicio de servicio de 10 cableados para el Ã¡rea de C&P - Pin 6778. | F3: MXN | G3: 30185.73 | H3: 1 | J3: 3935.31 | K3: 553.97 | L3: =+M3+Q3 -> 21866.83 | M3: 0 | N3: 1599.84 | O3: =+N3*H3 -> 1599.84 | P3: 6719.06 | Q3: 21866.83 | R3: 28585.89 | S3: 28031.92 | T3: 1.059 | U3: 24650.58 | V3: 0.8166 | W3: 0.36
A4: 13115 | B4: HECTOR VELA | C4: LANDIS & GYR | D4: 46111 | E4: SUMINISTRO E INSTALACION DE CHAROLA (AREA NUEVA DE PRODUCCION PLANTA 2) Actualizado 2 | F4: MXN | G4: 121920.27 | H4: 1 | J4: 16327.26 | K4: 14557.27 | L4: =+M4+Q4 -> 30907.93 | M4: 19467.8 | N4: 49806.38 | O4: =+N4*H4 -> 49806.38 | P4: 41205.96 | Q4: 11440.13 | R4: 52644.12 | S4: 38086.85 | T4: 0.4463 | U4: 36316.86 | V4: 0.2979 | W4: 0.35
A5: 13112 | B5: RAMIRO LEE | C5: CORNING OPTICAL COMMUNICATIONS | D5: 46111 | E5: #13112 - PO 4502009031 - RENTA DE 1 MES POR 1 PLATAFORMA EN RAM - Marzo - Pin 8063. | F5: MXN | G5: 19710 | H5: 1 | J5: 2917.6 | K5: 4391.86 | L5: =+M5+Q5 -> 0 | M5: 0 | N5: 21799.26 | O5: =+N5*H5 -> 21799.26 | P5: ($ -2,089.26) | Q5: 0 | R5: ($ -2,089.26) | S5: ($ -6,481.12) | T5: (-32.88 %) | U5: ($ -6,481.12) | V5: (-32.88 %) | W5: 0.4
A6: 13111 | B6: ALFREDO PALOMINO | C6: ALCOM ELECTRONICOS DE MEXICO | D6: 46106 | E6: Pantalla privacidad portatil 14 pulgadas 16:10 K55254WW KENSINGTON | F6: MXN | G6: 1511.11 | H6: 1 | J6: 392.23 | K6: 417.85 | L6: =+M6+Q6 -> 0 | M6: 0 | N6: 1049.06 | O6: =+N6*H6 -> 1049.06 | P6: 462.05 | Q6: 0 | R6: 462.05 | S6: 44.2 | T6: 0.0293 | U6: 44.2 | V6: 0.0293 | W6: 0.7
A7: 13110 | B7: ALFREDO PALOMINO | C7: ALCOM ELECTRONICOS DE MEXICO | D7: 46106 | E7: Blackwire Modelo: C3225 | F7: MXN | G7: 2125.05 | H7: 1 | J7: 404.55 | K7: 455.13 | L7: =+M7+Q7 -> 0 | M7: 0 | N7: 1282.11 | O7: =+N7*H7 -> 1282.11 | P7: 842.94 | Q7: 0 | R7: 802.94 | S7: 347.81 | T7: 0.1637 | U7: 347.81 | V7: 0.1637 | W7: 0
A8: 13109 | B8: ORLANDO MARTINEZ | C8: ALCOM ELECTRONICOS DE MEXICO | D8: 46112 | E8: instalacion de alarma para escalera electrica awp30 | F8: MXN | G8: 7620.8 | H8: 1 | J8: 815.09 | K8: 1431.72 | L8: =+M8+Q8 -> 6076.46 | M8: 0 | N8: 7385.79 | O8: =+N8*H8 -> 7385.79 | P8: ($ -5,841.45) | Q8: 6076.46 | R8: 235.01 | S8: ($ -1,196.71) | T8: (-15.70 %) | U8: ($ -1,196.71) | V8: (-15.70 %) | W8: 0
A9: 13108 | B9: HECTOR VELA | C9: HOFFMAN SCHROFF MANUFACTURING | D9: 46098 | E9: VENTA DE CAMARA EMEET (SMARTCAM) S800-4K | F9: MXN | G9: 3426.84 | H9: 1 | J9: 469 | K9: 459.46 | L9: =+M9+Q9 -> 0 | M9: 0 | N9: 1981.9 | O9: =+N9*H9 -> 1981.9 | P9: 1444.94 | Q9: 0 | R9: 1444.94 | S9: 985.48 | T9: 0.4244 | U9: 975.94 | V9: 0.2848 | W9: 0.49
A10: 13107 | B10: ORLANDO MARTINEZ | C10: CORNING OPTICAL COMMUNICATIONS | D10: 46099 | E10: INSTALACION DE 4 NODOS DE RED PARA APS EN PLANTA RCS | F10: MXN | G10: 40293.37 | H10: 1 | J10: 3535.61 | K10: 1924.02 | L10: 0 | M10: 2939.59 | N10: 6604.36 | O10: =+N10*H10 -> 6604.36 | P10: 33689.01 | Q10: ($ -2,939.59) | R10: 30749.42 | S10: 28825.4 | T10: 0.8031 | U10: 27213.81 | V10: 0.6754 | W10: 0.95
A11: 13103 | B11: ALFREDO PALOMINO | C11: ALCOM ELECTRONICOS DE MEXICO | D11: 46104 | E11: Renta de Escalera ElÃ©ctrica Por Mes MARZO 2026 | F11: MXN | G11: 10939.5 | H11: 1 | J11: 0 | K11: 0 | L11: =+M11+Q11 -> 0 | M11: 0 | N11: 10939.5 | O11: =+N11*H11 -> 10939.5 | P11: 0 | Q11: 0 | R11: 0 | S11: 0 | T11: 0 | U11: 0 | V11: 0 | W11: 0.1
A12: 13087 | B12: RAMIRO LEE | C12: MONROE MEXICO | D12: 46091 | E12: P#13087 -PO #4502126455 - Movimientos en Ã¡rea de empaque â€“ Planta #3 - Ãrea ContenciÃ³n embarques - Pin 1212. | F12: MXN | G12: 43213.34 | H12: 1 | J12: 7587.86 | K12: 5924.37 | L12: =+M12+Q12 -> 34819.78 | M12: 11739.15 | N12: 2869.75 | O12: =+N12*H12 -> 2869.75 | P12: 5523.81 | Q12: 23080.63 | R12: 28604.44 | S12: 22680.07 | T12: 0.7004 | U12: 21016.58 | V12: 0.4863 | W12: 0.41
A13: 13072 | B13: ALFREDO PALOMINO | C13: ALCOM ELECTRONICOS DE MEXICO | D13: 46106 | E13: CotizaciÃ³n Diademas Plantronics C3225 | F13: MXN | G13: 2126.1 | H13: 1 | J13: 429.04 | K13: 455.23 | L13: =+M13+Q13 -> 0 | M13: 0 | N13: 1282.73 | O13: =+N13*H13 -> 1282.73 | P13: 843.37 | Q13: 0 | R13: 803.37 | S13: 348.14 | T13: 0.1637 | U13: 348.14 | V13: 0.1637 | W13: 0.9
A14: 13067 | B14: ALFREDO PALOMINO | C14: ALCOM ELECTRONICOS DE MEXICO | D14: 46098 | E14: Cotizar Cables - Adaptadores | F14: MXN | G14: 1182.72 | H14: 1 | J14: 336.02 | K14: 352.99 | L14: =+M14+Q14 -> 0 | M14: 0 | N14: 643.67 | O14: =+N14*H14 -> 643.67 | P14: 539.05 | Q14: 0 | R14: 419.05 | S14: 66.06 | T14: 0.0559 | U14: 66.06 | V14: 0.0559 | W14: 0
A15: 13061 | B15: ALFREDO PALOMINO | C15: ALCOM ELECTRONICOS DE MEXICO | D15: 46098 | E15: INSTALACION DE CAMARA EN RECICLADOS | F15: MXN | G15: 10274.98 | H15: 1 | J15: 1365.47 | K15: 1133.32 | L15: =+M15+Q15 -> 4220.58 | M15: 1049.86 | N15: 4142.71 | O15: =+N15*H15 -> 4142.71 | P15: 1911.69 | Q15: 3170.72 | R15: 5081.53 | S15: 3948.21 | T15: 0.5171 | U15: 3716.06 | V15: 0.3617 | W15: 0.44
A16: 13058 | B16: HECTOR VELA | C16: CARPLASTIC | D16: 46092 | E16: VENTA DE LICENCIA DE DESARROLLO WINDOWS GESTION MONITORIZACION TIEMPOS DE DESCANSO | F16: MXN | G16: 31800 | H16: 1 | J16: 2100 | K16: 2529.3 | L16: =+M16+Q16 -> 0 | M16: 0 | N16: 24770 | O16: =+N16*H16 -> 24770 | P16: 7030 | Q16: 0 | R16: 7030 | S16: 4500.7 | T16: 0.1415 | U16: 4500.7 | V16: 0.1415 | W16: 0.59
A17: 13041 | B17: RAMIRO LEE | C17: CORNING MONTERREY | D17: 46093 | E17: P#13041 - PO PO 4502002585 - #RFQReq 216457 - InstalaciÃ³n de 12 nodos de red planta MTA Pin 1925. | F17: MXN | G17: 34601.16 | H17: 1 | J17: 3935.31 | K17: 3468.26 | L17: =+M17+Q17 -> 26282.26 | M17: 5561.39 | N17: 9913.33 | O17: =+N17*H17 -> 9913.33 | P17: ($ -1,594.43) | Q17: 20720.87 | R17: 19126.44 | S17: 15658.18 | T17: 0.5663 | U17: 15191.13 | V17: 0.439 | W17: 0.36
A18: 13042 | B18: RAMIRO LEE | C18: CORNING MONTERREY | D18: 46099 | F18: MXN | G18: 5765.14 | H18: 1 | J18: 1283.35 | K18: 308.06 | L18: =+M18+Q18 -> 5765.14 | M18: 0 | N18: 305.55 | O18: =+N18*H18 -> 305.55 | P18: -305.55 | Q18: 5765.14
A19: 13035 | B19: RAMIRO LEE | C19: CORNING OPTICAL COMMUNICATIONS | D19: 46112 | E19: PV#13035 - PO # 4501933175 - #RFQReq 197376 - ProvisiÃ³n de Personal TÃ©cnico Para Actividades de InstalaciÃ³n de Nodos de Red - (Marzo) - PIN 5312. | F19: MXN | G19: 925190.62 | H19: 1 | J19: 91420.12 | K19: 117026.27 | L19: =+M19+Q19 -> 873241.9 | M19: 158775.36 | N19: 363932.94 | O19: =+N19*H19 -> 363932.94 | P19: ($ -311,984.22) | Q19: 714466.54 | R19: 402482.32 | S19: 285456.05 | T19: 0.3085 | U19: 285456.05 | V19: 0.3085 | W19: 0.07
A20: 13030 | B20: ORLANDO MARTINEZ | C20: ALPS ALPINE NORTH AMERICA | D20: 46105 | E20: Renta montacargas 15 mil libras | F20: USD | G20: 893.1 | H20: 17.17 | I20: =+G20*H20 -> 15334.527 | J20: 68.9 | K20: 113.56 | L20: =+M20+Q20 -> 0 | M20: 0 | N20: 618.83 | O20: =+N20*H20 -> 10625.311 | P20: 274.27 | Q20: 0 | R20: 274.27 | S20: 160.71 | T20: 0.1799 | U20: 160.71 | V20: 0.1799 | W20: 0
A21: 13019 | B21: HECTOR VELA | C21: SMP ENGINE MANAGEMENT | D21: 46104 | E21: REUBICACION DE TUBERIA POR EXPANCION DE TALLER | F21: MXN | G21: 14989.13 | H21: 1 | J21: 2563.1 | K21: 2598.79 | L21: =+M21+Q21 -> 9251.35 | M21: 5577.79 | N21: 2671.63 | O21: =+N21*H21 -> 2671.63 | P21: 3066.15 | Q21: 3673.56 | R21: 6739.71 | S21: 4140.92 | T21: 0.2763 | U21: 4140.92 | V21: 0.2763 | W21: 0.35
A22: 13010 | B22: HECTOR VELA | C22: IMPRESORA DONNECO INTERNACIONAL | D22: 46091 | E22: VENTA DE MATERIAL DE RED PANDUIT (JACK COLOR AZUL Y FACEPLATE DE 4 Y 2 ESPACIOS) | F22: MXN | G22: 3912.51 | H22: 1 | J22: 574.76 | K22: 580.98 | L22: =+M22+Q22 -> 0 | M22: 0 | N22: 2699.4 | O22: =+N22*H22 -> 2699.4 | P22: 1213.11 | Q22: 0 | R22: 1213.11 | S22: 632.13 | T22: 0.1616 | U22: 632.13 | V22: 0.1616 | W22: 0.57
A23: 13004 | B23: ALFREDO PALOMINO | C23: ALCOM ELECTRONICOS DE MEXICO | D23: 46091 | E23: CotizaciÃ³n protector de privacidad | F23: MXN | G23: 715.89 | H23: 1 | J23: 304.74 | K23: 314.61 | L23: =+M23+Q23 -> 0 | M23: 0 | N23: 496.99 | O23: =+N23*H23 -> 496.99 | P23: 218.9 | Q23: 0 | R23: 218.9 | S23: ($ -95.71) | T23: (-13.37 %) | U23: ($ -95.71) | V23: (-13.37 %) | W23: 0.7
A24: 12979 | B24: HECTOR VELA | C24: CEBAL AMERICAS DE REYNOSA | D24: 46084 | E24: INSTALACION DE 1 NODO DE RED AREA DE PRODUCCION (LINEA 10) | F24: MXN | G24: 9920.03 | H24: 1 | J24: 1394.26 | K24: 1405.62 | L24: =+M24+Q24 -> 4625.68 | M24: 2099.7 | N24: 4059.06 | O24: =+N24*H24 -> 4059.06 | P24: 1235.29 | Q24: 2525.98 | R24: 3760.24 | S24: 2354.62 | T24: 0.2374 | U24: 2354.62 | V24: 0.2374 | W24: 0.35
A25: 12959 | B25: ALFREDO PALOMINO | C25: ALPS ALPINE NORTH AMERICA | D25: 46111 | E25: Material para Red JosÃ© Rafael H. | F25: USD | G25: 2595.71 | H25: 17.2 | I25: =+G25*H25 -> 44646.212 | J25: 274.1 | K25: 275.69 | L25: =+M25+Q25 -> 0 | M25: 0 | N25: 1632.24 | O25: =+N25*H25 -> 28074.528 | P25: 963.47 | Q25: 0 | R25: 963.37 | S25: 687.68 | T25: 0.2649 | U25: 687.68 | V25: 0.2649 | W25: 0.6
A26: 12956 | B26: ALFREDO PALOMINO | C26: ALPS ALPINE NORTH AMERICA | D26: 46099 | E26: MATERIAL REQUERIDO PARA SPARE PARTS MD1 | F26: USD | G26: 977.47 | H26: 17.23 | I26: =+G26*H26 -> 16841.808 | J26: 112.26 | K26: 116.86 | L26: =+M26+Q26 -> 0 | M26: 0 | N26: 639.66 | O26: =+N26*H26 -> 11021.342 | P26: 337.81 | Q26: 0 | R26: 337.8 | S26: 220.94 | T26: 0.226 | U26: 220.94 | V26: 0.226 | W26: 0.6
A27: 12945 | B27: HECTOR VELA | C27: HOFFMAN SCHROFF MANUFACTURING | D27: 46085 | E27: VENTA DE MOUSE ERGONOMICO PROTO ARC INALAMBRICO (EM11 NL) | F27: MXN | G27: 14197.68 | H27: 1 | J27: 1525.42 | K27: 1004.15 | L27: =+M27+Q27 -> 0 | M27: 0 | N27: 4647.33 | O27: =+N27*H27 -> 4647.33 | P27: 9550.35 | Q27: 0 | R27: 9550.35 | S27: 8546.2 | T27: 0.7094 | U27: 8024.93 | V27: 0.5652 | W27: 0.64
A28: 12933 | B28: ALFREDO PALOMINO | C28: ALCOM ELECTRONICOS DE MEXICO | D28: 46085 | E28: REPARACION DE CONTROL DE ACCESO DE ELEVADOR | F28: MXN | G28: 11528.96 | H28: 1 | J28: 1362.15 | K28: 859.36 | L28: =+M28+Q28 -> 9042.62 | M28: 1717.76 | N28: 1553.96 | O28: =+N28*H28 -> 1553.96 | P28: 932.38 | Q28: 7324.86 | R28: 8257.24 | S28: 7397.88 | T28: 0.7598 | U28: 6895.09 | V28: 0.5981 | W28: 0.6
A29: 12928 | B29: RAMIRO LEE | C29: CORNING OPTICAL COMMUNICATIONS | D29: 46111 | E29: #RFQReq:217109 - RENTA DE 1 MES POR 1 PLATAFORMA EN RAM - FEBRERO. | F29: MXN | G29: 19710 | H29: 1 | J29: 2917.6 | K29: 4391.86 | L29: =+M29+Q29 -> 0 | M29: 0 | N29: 21799.26 | O29: =+N29*H29 -> 21799.26 | P29: ($ -2,089.26) | Q29: 0 | R29: ($ -2,089.26) | S29: ($ -6,481.12) | T29: (-32.88 %) | U29: ($ -6,481.12) | V29: (-32.88 %) | W29: 0.4
A30: 12920 | B30: ALFREDO PALOMINO | C30: ALCOM ELECTRONICOS DE MEXICO | D30: 46108 | E30: REUBICACION DE TECLADO DE ALARMA | F30: MXN | G30: 12342.18 | H30: 1 | J30: 1186.4 | K30: 1064.01 | L30: =+M30+Q30 -> 9980.88 | M30: 3426.53 | N30: 590.3 | O30: =+N30*H30 -> 590.3 | P30: 1771 | Q30: 6554.35 | R30: 8325.35 | S30: 7261.34 | T30: 0.6845 | U30: 7138.95 | V30: 0.5784 | W30: 0.6
A31: 12914 | B31: ALFREDO PALOMINO | C31: PUBLICO EN GENERAL | D31: 46112 | E31: INSTALACION DE CENTRO DE CARGA | F31: MXN | G31: 21161.42 | H31: 1 | J31: 3035.32 | K31: 4752.12 | L31: =+M31-8058.02 -> 6330.87 | M31: 14388.89 | N31: 9252.78 | O31: =+N31*H31 -> 9252.78 | P31: 5577.77 | Q31: ($ -8,058.02) | R31: ($ -2,480.25) | S31: ($ -7,232.37) | T31: (-34.18 %) | U31: ($ -7,232.37) | V31: (-34.18 %) | W31: 0.25
A32: 12871 | B32: RAMIRO LEE | C32: CORNING OPTICAL COMMUNICATIONS | D32: 46111 | E32: P#12871 - PO PENDIENTE - #RFQReq:213529 - PIN 8397. | F32: MXN | G32: 250475.46 | H32: 1 | J32: 24171.83 | K32: 31738.69 | L32: =+M32+Q32 -> 0 | M32: 0 | N32: 166970.49 | O32: =+N32*H32 -> 166970.49 | P32: 83504.97 | Q32: 0 | R32: 83504.97 | S32: 51766.28 | T32: 0.2067 | U32: 51766.28 | V32: 0.2067 | W32: 0.97
A33: 12854 | B33: ALFREDO PALOMINO | C33: ALPS ALPINE NORTH AMERICA | D33: 46100 | E33: cotizacion bateria 01AV427 | F33: USD | G33: 506.97 | H33: 17.6 | I33: =+G33*H33 -> 8922.672 | J33: 64.91 | K33: 66.51 | L33: =+M33+Q33 -> 0 | M33: 0 | N33: 326.88 | O33: =+N33*H33 -> 5753.088 | P33: 180.09 | Q33: 0 | R33: 180.09 | S33: 113.58 | T33: 0.224 | U33: 113.58 | V33: 0.224 | W33: 0.6
A34: 12830 | B34: RAMIRO LEE | C34: CORNING OPTICAL COMMUNICATIONS | D34: 46091 | E34: P#12830 - PO 4501988766 -RFQReq 211179 - Pin 3421. | F34: MXN | G34: 67104.12 | H34: 1 | J34: 6624.9 | K34: 6654.98 | L34: =+M34+Q34 -> 0 | M34: 0 | N34: 33710.39 | O34: =+N34*H34 -> 33710.39 | P34: 33393.73 | Q34: 0 | R34: 30740.27 | S34: 24085.29 | T34: 0.3589 | U34: 24085.29 | V34: 0.3589 | W34: 0
A35: 12816 | B35: ALFREDO PALOMINO | C35: ALCOM ELECTRONICOS DE MEXICO | D35: 46087 | E35: LICENCIA Control de Acceso en Planta Falcon | F35: MXN | G35: 871.97 | H35: 1 | J35: 166.88 | K35: 167.21 | L35: =+M35+Q35 -> 0 | M35: 0 | N35: 573.79 | O35: =+N35*H35 -> 573.79 | P35: 298.18 | Q35: 0 | R35: 298.18 | S35: 130.97 | T35: 0.1502 | U35: 130.97 | V35: 0.1502 | W35: 0.55
A36: 12815 | B36: ALFREDO PALOMINO | C36: ALCOM ELECTRONICOS DE MEXICO | D36: 46087 | E36: CotizaciÃ³n de InstalaciÃ³n de Control de Acceso Planta Falcon | F36: MXN | G36: 23895.96 | H36: 1 | J36: 2962.49 | K36: 2802.72 | L36: =+M36+Q36 -> 12441.14 | M36: 6386.79 | N36: 7571.82 | O36: =+N36*H36 -> 7571.82 | P36: 3883 | Q36: 6054.35 | R36: 9937.35 | S36: 7134.63 | T36: 0.4225 | U36: 6974.86 | V36: 0.2919 | W36: 0.3
A37: 12785 | B37: CELESTE LANDA | C37: BCS-AIS ENSAMBLES MEXICO | D37: 46112 | E37: MOVIMIENTO DEL SISTEMA CCTV | F37: MXN | G37: 106943.39 | H37: 1 | J37: 11858.21 | K37: 9627.62 | L37: =+M37+Q37 -> 48734.2 | M37: 20884.75 | N37: 31198.82 | O37: =+N37*H37 -> 31198.82 | P37: 27010.37 | Q37: 27849.45 | R37: 54858.06 | S37: 45230.44 | T37: 0.5338 | U37: 42999.85 | V37: 0.4021 | W37: 0.5
A38: 12536 | B38: HECTOR VELA | C38: IMPRESORA DONNECO INTERNACIONAL | D38: 46092 | E38: SERVICIOS DE ADECUACIONES EXTRAS /INSTALACION DE VIDRIO PARA LOBBY/ INSTALACION DE 4 CAMARAS IP CASETA/ INSTALACION DE HERRERIA Y CONCERTINA TORNIQUETE/ INSTALACION DE VIDEO PORTERO VEHICULAR/ COMPRA DE 4 TELEVISORES DE 55" CON SU INSTALACION | F38: MXN | G38: 168254.39 | H38: 1 | J38: 17956.19 | K38: 23355.31 | L38: =+M38+Q38 -> 40529.2 | M38: 27742.04 | N38: 119705.77 | O38: =+N38*H38 -> 119705.77 | P38: 8019.42 | Q38: 12787.16 | R38: 19812.27 | S38: ($ -3,543.04) | T38: (-2.11 %) | U38: ($ -3,543.04) | V38: (-2.11 %) | W38: 0.42
A39: 12435 | B39: ALFREDO PALOMINO | C39: ALPS ALPINE NORTH AMERICA | D39: 46112 | E39: REUBICACION DE LINEA L21-L22 Y LN15-LN16 ABELARDO CASTILLO 08/10/2025 | F39: USD | G39: 3109.15 | H39: 18.35 | I39: =+G39*H39 -> 57052.903 | J39: 366.51 | K39: 315.3 | L39: =+M39+Q39 -> 1212.74 | M39: 575.62 | N39: 1129.91 | O39: =+N39*H39 -> 20733.849 | P39: 766.5 | Q39: 637.12 | R39: 1403.57 | S39: 1088.27 | T39: 0.4679 | U39: 1037.06 | V39: 0.3336 | W39: 0.3
A40: 12211 | B40: RAMIRO LEE | C40: CORNING OPTICAL COMMUNICATIONS | D40: 46112 | E40: P#12211 - PO PENDIENTE- RFQReq:199806 InstalaciÃ³n de tuberÃ­a, cableado y conexiones de para 16 tomas de corriente 208 V 30 AMP en raks de servidores. PIN 2350 | F40: MXN | G40: 114895.94 | H40: 1 | J40: 10066.79 | K40: 11357.01 | L40: =+M40+Q40 -> 38378.51 | M40: 8065.66 | N40: 39059.24 | O40: =+N40*H40 -> 39059.24 | P40: 37458.19 | Q40: 30312.85 | R40: 67771.04 | S40: 56414.03 | T40: 0.491 | U40: 56414.03 | V40: 0.491 | W40: 0
A41: 11566 | B41: ALFREDO PALOMINO | C41: ALCOM ELECTRONICOS DE MEXICO | D41: 46098 | E41: INSTALACION DE CHAROLA Y SERVICIOS DE RED, CONTROL DE ACCESO, CAMARAS EN AREA DE OFICINAS MD3. 2 parte | F41: MXN | G41: 303835.55 | H41: 1 | J41: 36834.02 | K41: 34401.16 | L41: =+M41-2652.9 -> 38854.72 | M41: 41507.62 | N41: 158966.01 | O41: =+N41*H41 -> 158966.01 | P41: 106014.82 | Q41: ($ -2,652.90) | R41: 101247.16 | S41: 66846 | T41: 0.3412 | U41: 64413.14 | V41: 0.212 | W41: 0.32
A42: 11549 | B42: CELESTE LANDA | C42: EMERSON TOOL AND APPLIANCE COMPANY | D42: 46112 | E42: IDFÂ´S Y CABLE DE FIBRA OPTICA | F42: USD | G42: 33540.16 | H42: 20.34 | I42: =+G42*H42 -> 682206.85 | J42: 3545.68 | K42: 3697.74 | L42: =+M42+Q42 -> 6077.96 | M42: 2005.71 | N42: 20401.57 | O42: =+N42*H42 -> 414967.93 | P42: 7060.63 | Q42: 4072.25 | R42: 11126.26 | S42: 7428.52 | T42: 0.2215 | U42: 7428.52 | V42: 0.2215 | W42: 0.57
H43: ALFREDO | I43: 127463.59 | O43: =SUM(O2:O42) -> 1609303.1
H44: CELESTE | I44: 682206.85 | L44: =SUBTOTAL(9,L2:L43) -> 1000354.4 | N44: 1117821.5 | P44: =SUBTOTAL(9,P2:P42) -> 166294.21
H45: ORLANDO | I45: 15334.527 | N45: 24749.09
N46: =+N44+N45*C47 -> 1557303.4
C47: 17.7575 | D47: MX | E47: USD
C48: MO COB | D48: 1215584.9 | E48: 7290.7
C49: MAT UTILIDAD | D49: 425701.43 | E49: 9582.77
D50: =+D49+D48 -> 1641286.3 | E50: =+(E48+E49)*C47 -> 299630.64
C51: TOTAL | D51: =+D50+E50 -> 1940917
C52: GASTO OP. | D52: 1350532.5
C53: UTILIDAD PROY | D53: =+D51-D52 -> 590384.46
G54: =SUBTOTAL(9,G2:G53) -> 1510851.5
G56: =+G42*17.7575 -> 595589.39
G57: =+I42-G56 -> 86617.463

Sheet ABRIL
A1: Id | B1: Promotor | C1: Cliente | D1: Fecha | E1: Descripcion | F1: Moneda | G1: TC | H1: Cotizado cliente | J1: Indirecto presupuestado | K1: Indirecto Real | L1: MO COB | M1: Mano obra real | N1: Material real | P1: Material utilidad | Q1: Mano obra utilidad | R1: Utilidad | S1: Utilidad despuÃ©s de indirectos | T1: % Utilidad antes de indirectos | U1: $ Utilidad a comision | V1: % Utilidad a comision | W1: % Utilidad promedio
A2: 13273 | B2: RAMIRO LEE | C2: CORNING MONTERREY | D2: 46142 | E2: #13273 - PO 4502020067 -#RFQReq220662 InstalaciÃ³n de servicio de 10 cableados para instalaciÃ³n de checadores MT - Pin 4299. | F2: MXN | G2: 1 | H2: 30290.86 | J2: 3935.31 | K2: 3554.31 | L2: =+M2+Q2 -> 21971.96 | M2: 6066.35 | N2: 9728.31 | O2: =+N2*G2 -> 9728.31 | P2: ($ -1,409.41) | Q2: 15905.61 | R2: 14496.2 | S2: 10941.89 | T2: 0.4911 | U2: 10560.89 | V2: 0.3486 | W2: 0.36
A3: 13272 | B3: HECTOR VELA | C3: HOFFMAN SCHROFF MANUFACTURING | D3: 46139 | E3: VENTA DE EQUIPOS DE AUDIO AURICULARES JABRA ENVOLVE 2 65 FLEX | F3: MXN | G3: 1 | H3: 7244.42 | J3: 658.64 | K3: 603.16 | L3: =+M3+Q3 -> 0 | M3: 0 | N3: 3438.79 | O3: =+N3*G3 -> 3438.79 | P3: 3805.63 | Q3: 0 | R3: 3805.63 | S3: 3202.47 | T3: 0.533 | U3: 3146.99 | V3: 0.4344 | W3: 0.37
A4: 13257 | B4: HECTOR VELA | C4: IMPRESORA DONNECO INTERNACIONAL | D4: 46139 | E4: VENTA DE ADAPTADOR DE DISPLAYPORT 4K A HDMI DP 1.2 UNA SOLA DIRECCION | F4: MXN | G4: 1 | H4: 2230.4 | J4: 440.8 | K4: 444.33 | L4: =+M4+Q4 -> 0 | M4: 0 | N4: 1477.69 | O4: =+N4*G4 -> 1477.69 | P4: 752.71 | Q4: 0 | R4: 521.59 | S4: 77.26 | T4: 0.0346 | U4: 77.26 | V4: 0.0346 | W4: 0.64
A5: 13252 | B5: CELESTE LANDA | C5: JOSE LEOPOLDO GARCIA GRACIA | D5: 46128 | E5: OXXO CAP CARLOS CANTU | F5: MXN | G5: 1 | H5: 2809.84 | J5: 506.9 | K5: 350.46 | L5: 0 | M5: 478.39 | N5: 0 | O5: =+N5*G5 -> 0 | P5: 2809.84 | Q5: ($ -478.39) | R5: 2331.45 | S5: 1980.99 | T5: 0.8854 | U5: 1824.55 | V5: 0.6493 | W5: 0.75
A6: 13251 | B6: CELESTE LANDA | C6: JOSE LEOPOLDO GARCIA GRACIA | D6: 46128 | E6: OXXO AVE FELIPE | F6: MXN | G6: 1 | H6: 2809.8 | J6: 506.9 | K6: 350.46 | L6: 0 | M6: 478.39 | N6: 0 | O6: =+N6*G6 -> 0 | P6: 2809.8 | Q6: ($ -478.39) | R6: 2331.41 | S6: 1980.95 | T6: 0.8854 | U6: 1824.51 | V6: 0.6493 | W6: 0.75
A7: 13243 | B7: HECTOR VELA | C7: IMPRESORA DONNECO INTERNACIONAL | D7: 46139 | E7: MANO DE OBRA POR REVISION Y DIAGNOSTICO DE ANTENA DE RADIO (PLANTA 1) | F7: MXN | G7: 1 | H7: 17062.39 | J7: 2428.68 | K7: 2189.11 | L7: =+M7+Q7 -> 17062.39 | M7: 5925.84 | N7: 904.3 | O7: =+N7*G7 -> 904.3 | P7: ($ -904.30) | Q7: 11136.55 | R7: 10232.25 | S7: 8043.14 | T7: 0.6137 | U7: 7803.57 | V7: 0.4574 | W7: 0
A8: 13241 | B8: ORLANDO MARTINEZ | C8: AMETEK LAMB MOTORES DE MEXICO | D8: 46127 | E8: Cable utp para exterior y Cinchos | F8: MXN | G8: 1 | H8: 3891.08 | J8: 561.29 | K8: 561.29 | L8: =+M8+Q8 -> 0 | M8: 0 | N8: 1945.54 | O8: =+N8*G8 -> 1945.54 | P8: 1945.54 | Q8: 0 | R8: 1945.54 | S8: 1384.25 | T8: 0.5 | U8: 1384.25 | V8: 0.3557 | W8: 0
A9: 13238 | B9: ALFREDO PALOMINO | C9: ALCOM ELECTRONICOS DE MEXICO | D9: 46125 | E9: Renta de Escalera ElÃ©ctrica Por Mes ABRIL 2026 | F9: MXN | G9: 1 | H9: 10939.5 | J9: 0 | K9: 0 | L9: =+M9+Q9 -> 0 | M9: 0 | N9: 10939.5 | O9: =+N9*G9 -> 10939.5 | P9: 0 | Q9: 0 | R9: 0 | S9: 0 | T9: 0 | U9: 0 | V9: 0 | W9: 0.1
A10: 13235 | B10: CELESTE LANDA | C10: CONSORCIO PETROLERO 5M DEL GOLFO | D10: 46139 | E10: REVISION DEL CONTROL DE ACCESO | F10: MXN | G10: 1 | H10: 4632.33 | J10: 695.64 | K10: 488.33 | L10: =+M10+Q10 -> 4399.98 | M10: 1012.82 | N10: 160.24 | O10: =+N10*G10 -> 160.24 | P10: 72.11 | Q10: 3387.16 | R10: 3459.27 | S10: 2970.94 | T10: 0.7915 | U10: 2763.63 | V10: 0.5966 | W10: 0.45
A11: 13233 | B11: ANA MARGARITA SAHAGUN | C11: CORNING OPTICAL COMMUNICATIONS | D11: 46141 | E11: Goods Plant:RY1 #RFQReq:217508 #Vendor:251337# | F11: MXN | G11: 1 | H11: 21749.76 | J11: 3119.76 | K11: 3119.76 | L11: =+M11+Q11 -> 0 | M11: 0 | N11: 15104 | O11: =+N11*G11 -> 15104 | P11: 6645.76 | Q11: 0 | R11: 6645.76 | S11: 3526 | T11: 0.3056 | U11: 3526 | V11: 0.1621 | W11: 0.44
A12: 13232 | B12: ORLANDO MARTINEZ | C12: PUBLICO EN GENERAL | D12: 46128 | F12: MXN | G12: 1 | H12: 2037.82 | J12: 500.82 | K12: 496.89 | L12: =+M12+Q12 -> 0 | M12: 0 | N12: 1543.1 | O12: =+N12*G12 -> 1543.1 | P12: 494.72 | Q12: 0 | R12: 494.36 | S12: ($ -2.53) | T12: 0.2445 | U12: ($ -6.46) | V12: (-0.32 %) | W12: 0.3
A13: 13229 | B13: HECTOR VELA | C13: LANDIS & GYR | D13: 46139 | E13: VENTA DE TARJETAS DE CONTROL DE ACCESO (1326LGSMV PROXCARD) Actualizado | F13: MXN | G13: 1 | H13: 15747 | J13: 863.42 | K13: 840.38 | L13: =+M13+Q13 -> 0 | M13: 0 | N13: 11346 | O13: =+N13*G13 -> 11346 | P13: 4401 | Q13: 0 | R13: 4400.83 | S13: 3560.45 | T13: 0.2809 | U13: 3537.41 | V13: 0.2246 | W13: 0.3
A14: 13222 | B14: ALFREDO PALOMINO | C14: ALCOM ELECTRONICOS DE MEXICO | D14: 46140 | E14: CotizaciÃ³n Mouse InalÃ¡mbrico NYIEFADA | F14: MXN | G14: 1 | H14: 2885.33 | J14: 451.6 | K14: 500.46 | L14: =+M14+Q14 -> 0 | M14: 0 | N14: 1565.39 | O14: =+N14*G14 -> 1565.39 | P14: 1319.94 | Q14: 0 | R14: 1105.74 | S14: 605.28 | T14: 0.2098 | U14: 605.28 | V14: 0.2098 | W14: 0
A15: 13212 | B15: RAMIRO LEE | C15: BLACK & DECKER DE REYNOSA | D15: 46140 | E15: P#13212 -OC #619826 - Servicio de Reemplazo De Chapas MagnÃ©ticas, Cierra Puerta y BotÃ³n Verde Puerta Peatonal a Planta â€“ Caseta Principal - Pin 8080. | F15: MXN | G15: 1 | H15: 24041.73 | J15: 2966.22 | K15: 3104.98 | L15: =+M15+Q15 -> 12410.3 | M15: 7440.13 | N15: 6516 | O15: =+N15*G15 -> 6516 | P15: 5115.43 | Q15: 4970.17 | R15: 10085.24 | S15: 6980.26 | T15: 0.2903 | U15: 6980.26 | V15: 0.2903 | W15: 0.6
A16: 13206 | B16: ALFREDO PALOMINO | C16: WOODCRAFTERS HOME PRODUCTS | D16: 46125 | E16: COTIZACION Laptop HP 14-DQ0518LA | F16: MXN | G16: 1 | H16: 13991.6 | J16: 2148.86 | K16: 1625.54 | L16: =+M16+Q16 -> 0 | M16: 0 | N16: 7239.66 | O16: =+N16*G16 -> 7239.66 | P16: 6751.94 | Q16: 0 | R16: 6751.94 | S16: 5126.4 | T16: 0.52 | U16: 4603.08 | V16: 0.329 | W16: 0.4
A17: 13203 | B17: RAMIRO LEE | C17: BLACK & DECKER DE REYNOSA | D17: 46140 | E17: P#13203 - OC#619790 - Servicio de Reemplazo de BotÃ³n de Puerta Laboratorio MetrologÃ­a. - Pin 4078 | F17: MXN | G17: 1 | H17: 8667.27 | J17: 1414.24 | K17: 1186.93 | L17: =+M17+Q17 -> 6364.04 | M17: 3091.12 | N17: 236.25 | O17: =+N17*G17 -> 236.25 | P17: 2066.98 | Q17: 3272.92 | R17: 5339.54 | S17: 4152.61 | T17: 0.6423 | U17: 3925.3 | V17: 0.4529 | W17: 0.5
A18: 13200 | B18: RAMIRO LEE | C18: BLACK & DECKER DE REYNOSA | D18: 46141 | E18: #13200 - OC 619793 - Servicio de Reemplazo de CÃ¡mara PTZ IP Domo 52 AlmacÃ©n Residuos Peligrosos, Pin 2602. | F18: MXN | G18: 1 | H18: 66005.81 | J18: 7438.32 | K18: 5274.88 | L18: =+M18+Q18 -> 22195.52 | M18: 5237.93 | N18: 19843.21 | O18: =+N18*G18 -> 19843.21 | P18: 23967.08 | Q18: 16957.59 | R18: 40924.61 | S18: 35649.73 | T18: 0.6528 | U18: 33486.29 | V18: 0.5073 | W18: 0.48
A19: 13188 | B19: HECTOR VELA | C19: CARPLASTIC | D19: 46141 | E19: REPARACION DE PANTALLA DE CELULAR SAMSUNG S24 ULTRA (SM-S2928B) | F19: MXN | G19: 1 | H19: 12460 | J19: 1301 | K19: 1130 | L19: =+M19+Q19 -> 0 | M19: 0 | N19: 7000 | O19: =+N19*G19 -> 7000 | P19: 5460 | Q19: 0 | R19: 5460 | S19: 4330 | T19: 0.4519 | U19: 4159 | V19: 0.3338 | W19: 0.4
A20: 13187 | B20: CELESTE LANDA | C20: BCS-AIS ENSAMBLES MEXICO | D20: 46120 | E20: RENTA DE GENERADOR | F20: MXN | G20: 1 | H20: 2652 | J20: 462.16 | K20: 250 | L20: =+M20+Q20 -> 0 | M20: 0 | N20: 0 | O20: =+N20*G20 -> 0 | P20: 2652 | Q20: 0 | R20: 2652 | S20: 2402 | T20: 1.08 | U20: 2189.84 | V20: 0.8257 | W20: 0
A21: 13184 | B21: RAMIRO LEE | C21: CORNING OPTICAL COMMUNICATIONS | D21: 46125 | E21: #RFQReq:218489 PLATAFORMA EN RAM - Abril | F21: MXN | G21: 1 | H21: 19710 | J21: 2917.6 | K21: 4391.86 | L21: =+M21+Q21 -> 0 | M21: 0 | N21: 21799.26 | O21: =+N21*G21 -> 21799.26 | P21: ($ -2,089.26) | Q21: 0 | R21: ($ -2,089.26) | S21: ($ -6,481.12) | T21: (-32.88 %) | U21: ($ -6,481.12) | V21: (-32.88 %) | W21: 0.4
A22: 13176 | B22: ANA MARGARITA SAHAGUN | C22: CORNING OPTICAL COMMUNICATIONS | D22: 46140 | E22: Goods Plant:RY1 #RFQReq:218337 #Vendor:252772# | F22: MXN | G22: 1 | H22: 7386.3 | J22: 1217.86 | K22: 1083.7 | L22: =+M22+Q22 -> 0 | M22: 0 | N22: 4387.94 | O22: =+N22*G22 -> 4387.94 | P22: 2998.36 | Q22: 0 | R22: 2998.36 | S22: 1914.66 | T22: 0.4241 | U22: 1780.5 | V22: 0.2411 | W22: 0.45
A23: 13160 | B23: ANA MARGARITA SAHAGUN | C23: CORNING OPTICAL COMMUNICATIONS | D23: 46120 | E23: Goods Plant:RAM #RFQReq:217877 #Vendor:252276# | F23: MXN | G23: 1 | H23: 3397.5 | J23: 677.5 | K23: 677.5 | L23: =+M23+Q23 -> 0 | M23: 0 | N23: 2250 | O23: =+N23*G23 -> 2250 | P23: 1147.5 | Q23: 0 | R23: 1147.5 | S23: 470 | T23: 0.3377 | U23: 470 | V23: 0.1383 | W23: 0.51
A24: 13151 | B24: HECTOR VELA | C24: IMPRESORA DONNECO INTERNACIONAL | D24: 46127 | E24: VENTA DE CABLE VIAKON (DMI) Y CABLE PARA RED (PANDUIT) | F24: MXN | G24: 1 | H24: 50656.47 | J24: 1501.23 | K24: 1621.14 | L24: =+M24+Q24 -> 0 | M24: 0 | N24: 40704.83 | O24: =+N24*G24 -> 40704.83 | P24: 9951.64 | Q24: 0 | R24: 9951.08 | S24: 8329.94 | T24: 0.1644 | U24: 8329.94 | V24: 0.1644 | W24: 0.38
A25: 13145 | B25: CELESTE LANDA | C25: E&M INDUSTRIAL SUPPLIES | D25: 46125 | E25: NODOS DE RED MAQUINAS NUEVAS | F25: MXN | G25: 1 | H25: 25463.76 | J25: 3047.86 | K25: 3401.86 | L25: =+M25+Q25 -> 14721.82 | M25: 8548.74 | N25: 8478.94 | O25: =+N25*G25 -> 8478.94 | P25: 2263 | Q25: 6173.08 | R25: 8436.08 | S25: 5034.22 | T25: 0.1977 | U25: 5034.22 | V25: 0.1977 | W25: 0.36
A26: 13142 | B26: HECTOR VELA | C26: VEXIN GLOBAL SUPPLY | D26: 46126 | E26: COTIZACION DE PANTALLA INTERACTIVA HIKVISION (DS-D5C86RB/B2L(EDLA) | F26: MXN | G26: 1 | H26: 72959.46 | J26: 2083.68 | K26: 2190.39 | L26: =+M26+Q26 -> 0 | M26: 0 | N26: 59679.66 | O26: =+N26*G26 -> 59679.66 | P26: 13279.8 | Q26: 0 | R26: 13279.62 | S26: 11089.23 | T26: 0.152 | U26: 11089.23 | V26: 0.152 | W26: 0.3
A27: 13136 | B27: ORLANDO MARTINEZ | C27: CRISTALERA GONZALEZ MORELOS | D27: 46120 | E27: Reparacion Puerta | F27: MXN | G27: 1 | H27: 7469.14 | J27: 1235.29 | K27: 1796.3 | L27: =+M27-2028.42 -> 2786.5 | M27: 4814.92 | N27: 3344.75 | O27: =+N27*G27 -> 3344.75 | P27: 1337.89 | Q27: ($ -2,028.42) | R27: ($ -690.53) | S27: ($ -2,486.83) | T27: (-33.29 %) | U27: ($ -2,486.83) | V27: (-33.29 %) | W27: 0.4
A28: 13134 | B28: ORLANDO MARTINEZ | C28: ALCOM ELECTRONICOS DE MEXICO | D28: 46125 | E28: switches 5 puertos | F28: MXN | G28: 1 | H28: 1311.93 | J28: 319.97 | K28: 342.22 | L28: =+M28+Q28 -> 0 | M28: 0 | N28: 576.37 | O28: =+N28*G28 -> 576.37 | P28: 735.56 | Q28: 0 | R28: 735.56 | S28: 393.34 | T28: 0.2998 | U28: 393.34 | V28: 0.2998 | W28: 0
A29: 13129 | B29: CELESTE LANDA | C29: E&M INDUSTRIAL SUPPLIES | D29: 46125 | E29: OFICINAS BERRENDO EQUIPOS NUEVOS | F29: MXN | G29: 1 | H29: 111565.98 | J29: 13167.73 | K29: 12607.39 | L29: =+M29+Q29 -> 22553.72 | M29: 8270.13 | N29: 66379.13 | O29: =+N29*G29 -> 66379.13 | P29: 22633.13 | Q29: 14283.59 | R29: 36916.54 | S29: 24309.15 | T29: 0.3359 | U29: 23748.81 | V29: 0.2129 | W29: 0.35
A30: 13128 | B30: RAMIRO LEE | C30: CORNING MONTERREY | D30: 46122 | E30: #13128 - PO 4502010687 -#RFQReq 217708 - InstalaciÃ³n de servicio de servicio de 16 cableados para el Ã¡rea de C&A Auto - Pin 1201 | F30: MXN | G30: 1 | H30: 43431.99 | J30: 3935.31 | K30: 3572.37 | L30: =+M30+Q30 -> 35113.09 | M30: 5273.58 | N30: 10824.77 | O30: =+N30*G30 -> 10824.77 | P30: ($ -2,505.87) | Q30: 29839.51 | R30: 27333.64 | S30: 23761.27 | T30: 0.6377 | U30: 23398.33 | V30: 0.5387 | W30: 0.36
A31: 13122 | B31: ORLANDO MARTINEZ | C31: PUBLICO EN GENERAL | D31: 46127 | E31: EXEDENTE INSTALACION SOLAR JAIME RODRIGUEZ | F31: MXN | G31: 1 | H31: 51618.73 | J31: 6603.07 | K31: 5691.27 | L31: =+M31+Q31 -> 0 | M31: 0 | N31: 34007.91 | O31: =+N31*G31 -> 34007.91 | P31: 17610.82 | Q31: 0 | R31: 17610.82 | S31: 11919.55 | T31: 0.3588 | U31: 11007.75 | V31: 0.2133 | W31: 0.3
A32: 13114 | B32: CELESTE LANDA | C32: E&M INDUSTRIAL SUPPLIES | D32: 46128 | E32: OFICINAS BERRENDO | F32: MXN | G32: 1 | H32: 69357.45 | J32: 8185.82 | K32: 6507.04 | L32: =+M32+Q32 -> 21025.8 | M32: 15831.97 | N32: 18327.07 | O32: =+N32*G32 -> 18327.07 | P32: 30004.58 | Q32: 5193.83 | R32: 35026.93 | S32: 28519.89 | T32: 0.5292 | U32: 26841.11 | V32: 0.387 | W32: 0.35
A33: 13094 | B33: RAMIRO LEE | C33: AUTOMOTIVE MAQUILADORA | D33: 46120 | E33: #13094 - OC ##63719 - NVR 32 Megapixel (8K) / 64 Canales IP / AcuSense - Pin, 2857. | F33: MXN | G33: 1 | H33: 80001.6 | J33: 8477.11 | K33: 8999.43 | L33: =+M33+Q33 -> 0 | M33: 0 | N33: 60340.89 | O33: =+N33*G33 -> 60340.89 | P33: 19660.71 | Q33: 0 | R33: 19660.71 | S33: 10661.28 | T33: 0.1333 | U33: 10661.28 | V33: 0.1333 | W33: 0.41
A34: 13082 | B34: RAMIRO LEE | C34: CAL-COMP ELECTRONICS DE MEXICO CO | D34: 46129 | E34: P#13082 - PO 26040900006 - Material para caseta de guardias - Pin 2317. | F34: MXN | G34: 1 | H34: 3648.32 | J34: 398.34 | K34: 303.04 | L34: =+M34+Q34 -> 0 | M34: 0 | N34: 408 | O34: =+N34*G34 -> 408 | P34: 3240.32 | Q34: 0 | R34: 3238.57 | S34: 2935.53 | T34: 0.9138 | U34: 2840.23 | V34: 0.7785 | W34: 0
A35: 13075 | B35: RAMIRO LEE | C35: MONROE MEXICO | D35: 46133 | E35: P#13075 - PO 4502127195 -InstalaciÃ³n de Control de Acceso Ãrea Tool Room - Pin 2406. | F35: MXN | G35: 1 | H35: 34272.99 | J35: 5341.41 | K35: 4940.63 | L35: =+M35+Q35 -> 15784.68 | M35: 8060.55 | N35: 10924.42 | O35: =+N35*G35 -> 10924.42 | P35: 7563.89 | Q35: 7724.13 | R35: 14709.75 | S35: 9769.12 | T35: 0.4409 | U35: 9368.34 | V35: 0.2733 | W35: 0.4
A36: 13062 | B36: ALFREDO PALOMINO | C36: ALCOM ELECTRONICOS DE MEXICO | D36: 46121 | E36: Cotizar Celular OPPO | F36: MXN | G36: 1 | H36: 15678.4 | J36: 1817.84 | K36: 1284.35 | L36: =+M36+Q36 -> 0 | M36: 0 | N36: 6464.66 | O36: =+N36*G36 -> 6464.66 | P36: 9213.74 | Q36: 0 | R36: 9213.74 | S36: 7929.39 | T36: 0.6217 | U36: 7395.9 | V36: 0.4717 | W36: 0.6
A37: 13049 | B37: RAMIRO LEE | C37: CORNING OPTICAL COMMUNICATIONS | D37: 46118 | E37: P#13049 -PO PO 4502007563 #RFQReq:216408 - SHIEYLA AGUILAR - PLANTA: RYDN - PIN 1073 | F37: MXN | G37: 1 | H37: 8416.39 | J37: 1008.14 | K37: 1039.89 | L37: =+M37+Q37 -> 0 | M37: 0 | N37: 4157.29 | O37: =+N37*G37 -> 4157.29 | P37: 4259.1 | Q37: 0 | R37: 3627.86 | S37: 2587.97 | T37: 0.3075 | U37: 2587.97 | V37: 0.3075 | W37: 0
A38: 13037 | B38: ORLANDO MARTINEZ | C38: PUBLICO EN GENERAL | D38: 46120 | E38: INSTALACION 14 PANELES CON INVERSOR DE 10K | F38: MXN | G38: 1 | H38: 150919.65 | J38: 12133.21 | K38: 11091.85 | L38: 0 | M38: 4193.79 | N38: 62257.19 | O38: =+N38*G38 -> 62257.19 | P38: 88662.46 | Q38: ($ -4,193.79) | R38: 84468.67 | S38: 73376.82 | T38: 0.5666 | U38: 72335.46 | V38: 0.4793 | W38: 0.5
A39: 13014 | B39: RAMIRO LEE | C39: CORNING OPTICAL COMMUNICATIONS | D39: 46133 | E39: #13014 - PO #4502002342 -Shield:2873648 - KARINA GAMBOA - MATEO SEQUERA - PLANTA RAM - PIN 5962. | F39: MXN | G39: 1 | H39: 93954.5 | J39: 9087.28 | K39: 11715.32 | L39: =+M39+Q39 -> 0 | M39: 0 | N39: 60343.76 | O39: =+N39*G39 -> 60343.76 | P39: 33610.74 | Q39: 0 | R39: 33610.74 | S39: 21895.42 | T39: 0.233 | U39: 21895.42 | V39: 0.233 | W39: 0
A40: 12901 | B40: RAMIRO LEE | C40: CORNING OPTICAL COMMUNICATIONS | D40: 46142 | E40: P#12901 - PO 4502001317 - #RFQReq:213388 - PLANTA: RYDN - RAM - Sheyla Aguilar - Pin 6923. | F40: MXN | G40: 1 | H40: 33533.37 | J40: 3404.13 | K40: 2178.59 | L40: =+M40+Q40 -> 0 | M40: 0 | N40: 10150.45 | O40: =+N40*G40 -> 10150.45 | P40: 23382.92 | Q40: 0 | R40: 23382.92 | S40: 21204.33 | T40: 0.7338 | U40: 19978.79 | V40: 0.5958 | W40: 0
A41: 12846 | B41: RAMIRO LEE | C41: CORNING OPTICAL COMMUNICATIONS | D41: 46120 | E41: P#12846 - PO 4501995083 - #RFQReq 212655 - BLANCA KARINA GAMBOA JEREZ - RYDN - RAM - PIN 1098. | F41: MXN | G41: 1 | H41: 33823.62 | J41: 3431.42 | K41: 3322.85 | L41: =+M41+Q41 -> 0 | M41: 0 | N41: 16172.91 | O41: =+N41*G41 -> 16172.91 | P41: 17650.71 | Q41: 0 | R41: 13507.79 | S41: 10184.94 | T41: 0.4026 | U41: 10076.37 | V41: 0.2979 | W41: 0
A42: 12754 | B42: CELESTE LANDA | C42: EMERSON TOOL AND APPLIANCE COMPANY | D42: 46140 | E42: INSTALACION DE APS | F42: MXN | G42: 1 | H42: 72776.3 | J42: 8343.31 | K42: 9048.34 | L42: =+M42+Q42 -> 24317.52 | M42: 16781.44 | N42: 32964.04 | O42: =+N42*G42 -> 32964.04 | P42: 15494.74 | Q42: 7536.08 | R42: 23030.82 | S42: 13982.48 | T42: 0.1921 | U42: 13982.48 | V42: 0.1921 | W42: 0.41
A43: 12718 | B43: CELESTE LANDA | C43: EMERSON TOOL AND APPLIANCE COMPANY | D43: 46134 | E43: RETRABAJO FIBRA OPTICA | F43: MXN | G43: 1 | H43: 95315.9 | J43: 10903.23 | K43: 7493.54 | L43: =+M43+Q43 -> 36476.28 | M43: 4195.36 | N43: 39765.76 | O43: =+N43*G43 -> 39765.76 | P43: 19073.86 | Q43: 32280.92 | R43: 51354.78 | S43: 43861.24 | T43: 0.5746 | U43: 40451.55 | V43: 0.4244 | W43: 0.46
A44: 12595 | B44: RAMIRO LEE | C44: CORNING OPTICAL COMMUNICATIONS | D44: 46141 | E44: P#12595 - PO 4501980121 -Plant RCS #RFQReqn209505 - InstalaciÃ³n de Fibra Ã“ptica en Planta CLS (RYR6) Pin 8165. | F44: MXN | G44: 1 | H44: 195871.24 | J44: 20198.41 | K44: 19894.41 | L44: =+M44+Q44 -> 136670.08 | M44: 26979.11 | N44: 44312.82 | O44: =+N44*G44 -> 44312.82 | P44: 14888.34 | Q44: 109690.97 | R44: 124579.31 | S44: 104684.9 | T44: 0.6376 | U44: 104380.9 | V44: 0.5329 | W44: 0.6
A45: 12511 | B45: CELESTE LANDA | C45: BCS-AIS ENSAMBLES MEXICO | D45: 46119 | E45: LIMPIEZA Y DEPURACION DE IDF'S | F45: MXN | G45: 1 | H45: 170421.75 | J45: 17137.77 | K45: 15121.31 | L45: =+M45+Q45 -> 71857.64 | M45: 41546.8 | N45: 38415.52 | O45: =+N45*G45 -> 38415.52 | P45: 60148.59 | Q45: 30310.84 | R45: 90415.11 | S45: 75293.8 | T45: 0.5424 | U45: 73277.34 | V45: 0.43 | W45: 0.6
A46: 11552 | B46: CELESTE LANDA | C46: EMERSON TOOL AND APPLIANCE COMPANY | D46: 46139 | E46: BAJADAS DERED PARA EQUIPOS | F46: USD | G46: 20.3388 | H46: 4280.09 | I46: =+G46*H46 -> 87051.894 | J46: 451.05 | K46: 536.64 | L46: =+M46+Q46 -> 1855.1 | M46: 1287.77 | N46: 1587.01 | O46: =+N46*G46 -> 32277.879 | P46: 837.98 | Q46: 567.33 | R46: 1405.25 | S46: 868.61 | T46: 0.2029 | U46: 868.61 | V46: 0.2029 | W46: 0.39
G47: =AVERAGE(G2:G46) -> 1.4297511 | H47: CELESTE | I47: 87051.894 | L47: =SUBTOTAL(9,L2:L46) -> 197207.86 | N47: =SUBTOTAL(9,N2:N46) -> 206077.71 | O47: =SUM(O2:O46) -> 788704.2 | P47: =SUBTOTAL(9,P2:P46) -> 158799.63
C51: 17.6969 | D51: MX | E51: USD
C52: MO COB | D52: 465711.32 | E52: 1855.1
C53: MAT UTILIDAD | D53: 489882.88 | E53: 837.98
D54: =+D53+D52 -> 955594.2 | E54: =+(E52+E53)*C51 -> 47659.167
C55: TOTAL | D55: =+D54+E54 -> 1003253.4
C56: GASTO OP. | D56: 1219130.5
C57: UTILIDAD PROY | D57: =+D55-D56 -> -215877.16
E61: Promotor | F61: MXN | G61: USD | H61: Total general
E62: ALFREDO PALOMINO | F62: 43494.83 | G62: 0 | H62: 43494.83
E63: CELESTE LANDA | F63: 557805.11 | G63: 4280.09 | H63: 633549.43
E64: HECTOR VELA | F64: 178360.14 | G64: 0 | H64: 178360.14
E65: ORLANDO MARTINEZ | F65: 217248.35 | G65: 0 | H65: 217248.35
E66: RAMIRO LEE | F66: 675669.69 | G66: 0 | H66: 675669.69
E67: ANA MARGARITA SAHAGUN | F67: 32533.56 | G67: 0 | H67: 32533.56
E68: Suma total | F68: 1705111.7 | G68: 4280.09 | H68: 1780856
E69: MAT REAL | F69: 756426.32 | G69: 1587.01 | H69: =+F69+G69*C51 -> 784511.48
H70: =+H68-H69 -> 996344.53

Sheet MAYO
A1: Id | B1: Promotor | C1: Cliente | D1: Fecha | E1: Descripcion | F1: Moneda | G1: TC | I1: Cotizado cliente | K1: Indirecto presupuestado | L1: Indirecto Real | M1: Mano obra real | N1: Material real | P1: Material utilidad | Q1: Mano obra utilidad | R1: Utilidad bruta | S1: Utilidad | T1: Utilidad despues de indirectos | U1: % Utilidad antes de indirectos | V1: $ Utilidad a comision | W1: % Utilidad a comision | X1: % Utilidad promedio
A2: 13462 | B2: RAMIRO LEE | C2: BLACK & DECKER DE REYNOSA | D2: 46170 | E2: #13462 - Proyecto de garantﾃｭa de #13212. - Pin 5524. | F2: MXN | G2: 17.3213 | H2: 1 | I2: 88.88 | J2: =+I2*H2 -> 88.88 | K2: 264.08 | L2: 1197.91 | M2: 4069.29 | N2: 583.49 | O2: =+H2*N2 -> 583.49 | P2: ($ -494.61) | Q2: ($ -4,069.29) | R2: ($ -494.61) | S2: ($ -4,565.63) | T2: ($ -5,763.54) | U2: (-6,484.63 %) | V2: ($ -5,763.54) | W2: (-6,484.63 %) | X2: 0.01
A3: 13454 | B3: HECTOR VELA | C3: IMPRESORA DONNECO INTERNACIONAL | D3: 46170 | E3: SUMINISTRO E INSTALACION DE CAMARA TURBO HD NUEVA Y CABLEADO NUEVO (AREA DE RAMPAS) | F3: MXN | G3: 17.3305 | H3: 1 | I3: 8670.47 | J3: =+I3*H3 -> 8670.47 | K3: 1920.88 | L3: 1866.84 | M3: 2099.7 | N3: 2661.94 | O3: =+H3*N3 -> 2661.94 | P3: 1382.85 | Q3: 2525.98 | R3: 6008.53 | S3: 3908.83 | T3: 2041.99 | U3: 0.4571 | V3: 1987.95 | W3: 0.2293 | X3: 0.35
A4: 13441 | B4: ALFREDO PALOMINO | C4: ALCOM ELECTRONICOS DE MEXICO | D4: 46167 | E4: Cotizar Adaptador | F4: MXN | G4: 17.3968 | H4: 1 | I4: 4002 | J4: =+I4*H4 -> 4002 | K4: 676.88 | L4: 670.65 | M4: 0 | N4: 2629.12 | O4: =+H4*N4 -> 2629.12 | P4: 1372.88 | Q4: 0 | R4: 1372.88 | S4: 1372.88 | T4: 702.23 | U4: 0.3446 | V4: 696 | W4: 0.1739 | X4: 0.5
A5: 13432 | B5: ORLANDO MARTINEZ | C5: ALCOM ELECTRONICOS DE MEXICO | D5: 46167 | E5: RENTA 2 PLATAFORMAS DE TIJERA POR DOS MESES | F5: MXN | G5: 17.3477 | H5: 1 | I5: 74764.8 | J5: =+I5*H5 -> 74764.8 | K5: 10218.64 | L5: 12212.36 | M5: 0 | N5: 74764.8 | O5: =+H5*N5 -> 74764.8 | P5: 0 | Q5: 0 | R5: 0 | S5: 0 | T5: ($ -12,212.36) | U5: (-16.33 %) | V5: ($ -12,212.36) | W5: (-16.33 %) | X5: 0.2
A6: 13410 | B6: HECTOR VELA | C6: HOFFMAN SCHROFF MANUFACTURING | D6: 46163 | E6: VENTA DE CABLE HDMI REDLEAFT (HDMIFO50) 50 MTS_2 | F6: MXN | G6: 17.213 | H6: 1 | I6: 12760.02 | J6: =+I6*H6 -> 12760.02 | K6: 787.82 | L6: 720.5 | M6: 0 | N6: 7350 | O6: =+H6*N6 -> 7350 | P6: 5410.02 | Q6: 0 | R6: 5410.02 | S6: 5410.02 | T6: 4689.52 | U6: 0.4293 | V6: 4622.2 | W6: 0.3622 | X6: 0.33
A7: 13387 | B7: HECTOR VELA | C7: CARPLASTIC | D7: 46171 | E7: VENTA DE BATERIAS BPA-12V24Ah (INDUSTRONIC) | F7: MXN | G7: 17.1908 | H7: 1 | I7: 131414.4 | J7: =+I7*H7 -> 131414.4 | K7: 8948.08 | L7: 8604.5 | M7: 0 | N7: 90050 | O7: =+H7*N7 -> 90050 | P7: 41364.4 | Q7: 0 | R7: 41364.4 | S7: 40513.8 | T7: 31909.3 | U7: 0.3109 | V7: 31565.72 | W7: 0.2402 | X7: 0.4
A8: 13386 | B8: ALFREDO PALOMINO | C8: ALCOM ELECTRONICOS DE MEXICO | D8: 46160 | E8: Renta de Escalera Elﾃｩctrica Por Mes MAYO 2026 | F8: MXN | G8: 17.1908 | H8: 1 | I8: 10939.5 | J8: =+I8*H8 -> 10939.5 | K8: 0 | L8: 0 | M8: 0 | N8: 10939.5 | O8: =+H8*N8 -> 10939.5 | P8: 0 | Q8: 0 | R8: 0 | S8: 0 | T8: 0 | U8: 0 | V8: 0 | W8: 0 | X8: 0.1
A9: 13382 | B9: ALFREDO PALOMINO | C9: ALCOM ELECTRONICOS DE MEXICO | D9: 46160 | E9: REVICION Y REPARACION DE CONTROL DE ACCESO DE ELEVADOR | F9: MXN | G9: 17.1908 | H9: 1 | I9: 8832.14 | J9: =+I9*H9 -> 8832.14 | K9: 1200.79 | L9: 789.75 | M9: 1185.01 | N9: 1818.14 | O9: =+H9*N9 -> 1818.14 | P9: 702.5 | Q9: 5126.49 | R9: 7014 | S9: 5828.99 | T9: 5039.24 | U9: 0.7065 | V9: 4628.2 | W9: 0.524 | X9: 0.4
A10: 13362 | B10: RAMIRO LEE | C10: AUTOMOTIVE MAQUILADORA | D10: 46153 | E10: PV#13362 - OC#65763 - PIN 6224 -ALEXANDRA BRINGAS | F10: MXN | G10: 17.253 | H10: 1 | I10: 3788.24 | J10: =+I10*H10 -> 3788.24 | K10: 732.29 | L10: 726.72 | M10: 0 | N10: 1511.48 | O10: =+H10*N10 -> 1511.48 | P10: 2276.76 | Q10: 0 | R10: 2276.76 | S10: 2196.76 | T10: 1470.04 | U10: 0.5814 | V10: 1464.47 | W10: 0.3866 | X10: 0
A11: 13356 | B11: ORLANDO MARTINEZ | C11: GM3 INDUSTRIAL SERVICES S. DE R.L. DE C.V | D11: 46170 | E11: CERRADURA INTELIGENTE | F11: MXN | G11: 17.3752 | H11: 1 | I11: 1712.7 | J11: =+I11*H11 -> 1712.7 | K11: 288.93 | L11: 288.84 | M11: 0 | N11: 1294.67 | O11: =+H11*N11 -> 1294.67 | P11: 418.03 | Q11: 0 | R11: 418.03 | S11: 418.03 | T11: 129.19 | U11: 0.2441 | V11: 129.1 | W11: 0.0754 | X11: 0.32
A12: 13347 | B12: HECTOR VELA | C12: INTERMEX MANUFACTURA | D12: 46161 | E12: SUMINISTRO E INSTALACION DE 5 NODOS DE RED AREA DE KRAKEN | F12: MXN | G12: 17.5157 | H12: 1 | I12: 26906.17 | J12: =+I12*H12 -> 26906.17 | K12: 3671.14 | L12: 4022.3 | M12: 3042.46 | N12: 14896.17 | O12: =+H12*N12 -> 14896.17 | P12: 2758.65 | Q12: 6208.89 | R12: 12010 | S12: 8967.54 | T12: 4945.24 | U12: 0.1838 | V12: 4945.24 | W12: 0.1838 | X12: 0.4
A13: 13346 | B13: ALFREDO PALOMINO | C13: ALCOM ELECTRONICOS DE MEXICO | D13: 46157 | E13: VENTA E INSTALACION DE BOTON EN TORNIQUETE | F13: MXN | G13: 17.5157 | H13: 1 | I13: 2282.37 | J13: =+I13*H13 -> 2282.37 | K13: 410.59 | L13: 412.33 | M13: 1106.91 | N13: 532.61 | O13: =+H13*N13 -> 532.61 | P13: 224.16 | Q13: 418.69 | R13: 1749.76 | S13: 642.85 | T13: 230.52 | U13: 0.101 | V13: 230.52 | W13: 0.101 | X13: 0.6
A14: 13338 | B14: HECTOR VELA | C14: NEWOPTIX RS | D14: 46170 | E14: GARANTIA DE CHAPA MAGNETICA (PUERTA PASILLO) | F14: MXN | G14: 17.5118 | H14: 1 | I14: 0.5 | J14: =+I14*H14 -> 0.5 | K14: 250.06 | L14: 520.25 | M14: 1286.84 | N14: 0 | O14: =+H14*N14 -> 0 | P14: 0.5 | Q14: ($ -1,286.84) | R14: 0.5 | S14: ($ -1,286.34) | T14: ($ -1,806.59) | U14: (-361,318.00 %) | V14: ($ -1,806.59) | W14: (-361,318.00 %) | X14: 0.35
A15: 13320 | B15: ALFREDO PALOMINO | C15: WOODCRAFTERS HOME PRODUCTS | D15: 46147 | E15: Cotizaciﾃｳn M1023-19 ACTUALIZACION ATR-11 | F15: MXN | G15: 17.4948 | H15: 1 | I15: 1471.5 | J15: =+I15*H15 -> 1471.5 | K15: 395.33 | L15: 394.13 | M15: 0 | N15: 900.75 | O15: =+H15*N15 -> 900.75 | P15: 570.75 | Q15: 0 | R15: 570.75 | S15: 569 | T15: 174.87 | U15: 0.3875 | V15: 173.67 | W15: 0.118 | X15: 0.62
A16: 13298 | B16: HECTOR VELA | C16: HOFFMAN SCHROFF MANUFACTURING | D16: 46170 | E16: VENTA DE LICENCIA PERPETUA SOFTWARE LABEL MATRIX (RFQ:26042319) | F16: MXN | G16: 17.4052 | H16: 1 | I16: 20250 | J16: =+I16*H16 -> 20250 | K16: 850 | L16: 820 | M16: 0 | N16: 14000 | O16: =+H16*N16 -> 14000 | P16: 6250 | Q16: 0 | R16: 6250 | S16: 6250 | T16: 5430 | U16: 0.3101 | V16: 5400 | W16: 0.2667 | X16: 0.35
A17: 13297 | B17: ANA MARGARITA SAHAGUN | C17: CORNING OPTICAL COMMUNICATIONS | D17: 46160 | E17: Goods Plant:RAM #RFQReq:220596 #Vendor:256352# | F17: MXN | G17: 17.4052 | H17: 1 | I17: 2797.43 | J17: =+I17*H17 -> 2797.43 | K17: 574.1 | L17: 544.31 | M17: 0 | N17: 1549 | O17: =+H17*N17 -> 1549 | P17: 1248.43 | Q17: 0 | R17: 1248.43 | S17: 1248.43 | T17: 704.12 | U17: 0.4569 | V17: 674.33 | W17: 0.2411 | X17: 0.64
A18: 13288 | B18: HECTOR VELA | C18: HOFFMAN SCHROFF MANUFACTURING | D18: 46153 | E18: VENTA DE AURICULARES JABRA ENVOLVE2 65 FLEX | F18: MXN | G18: 17.3587 | H18: 1 | I18: 5508.81 | J18: =+I18*H18 -> 5508.81 | K18: 519.76 | L18: 514.61 | M18: 0 | N18: 3820.32 | O18: =+H18*N18 -> 3820.32 | P18: 1688.49 | Q18: 0 | R18: 1688.49 | S18: 1688.49 | T18: 1173.88 | U18: 0.3074 | V18: 1168.73 | W18: 0.2122 | X18: 0.38
A19: 13283 | B19: CELESTE LANDA | C19: E&M INDUSTRIAL SUPPLIES | D19: 46147 | E19: NODO MAQUINA NUEVA | F19: MXN | G19: 17.3323 | H19: 1 | I19: 7140.41 | J19: =+I19*H19 -> 7140.41 | K19: 1039.38 | L19: 950 | M19: 2021 | N19: 1722.45 | O19: =+H19*N19 -> 1722.45 | P19: 1212.8 | Q19: 2184.16 | R19: 5417.96 | S19: 3396.96 | T19: 2446.96 | U19: 0.4883 | V19: 2357.58 | W19: 0.3302 | X19: 0.35
A20: 13267 | B20: ALFREDO PALOMINO | C20: MONROE MEXICO | D20: 46160 | E20: 2 CABLEADOS PARA IMPRESORAS PLANTA 2 | F20: MXN | G20: 17.2723 | H20: 1 | I20: 14010.74 | J20: =+I20*H20 -> 14010.74 | K20: 1773.16 | L20: 1098.36 | M20: 2030.32 | N20: 2637.46 | O20: =+H20*N20 -> 2637.46 | P20: 2962.96 | Q20: 6380 | R20: 11373.28 | S20: 9342.96 | T20: 8244.6 | U20: 0.715 | V20: 7569.8 | W20: 0.5403 | X20: 0.4
A21: 13239 | B21: HECTOR VELA | C21: INTERMEX MANUFACTURA | D21: 46163 | E21: SUMINISTRO E INSTALACION DE NODOS DE RED EN EL AREA DE (IPLANT / ELECTRONICS / EMBARQUES) | F21: MXN | G21: 17.3033 | H21: 1 | I21: 38485.39 | J21: =+I21*H21 -> 38485.39 | K21: 5303.27 | L21: 4708.91 | M21: 4056.6 | N21: 14731.38 | O21: =+H21*N21 -> 14731.38 | P21: 9876.98 | Q21: 9820.43 | R21: 23754.01 | S21: 19697.41 | T21: 14988.5 | U21: 0.5273 | V21: 14394.14 | W21: 0.374 | X21: 0.37
A22: 13237 | B22: ORLANDO MARTINEZ | C22: MARIA ANTONIETA NUﾃ薦Z PACHECO | D22: 46156 | E22: reparacion de ap naranjos | F22: MXN | G22: 17.3593 | H22: 1 | I22: 26803.03 | J22: =+I22*H22 -> 26803.03 | K22: 3372.2 | L22: 2503.81 | M22: 4056.6 | N22: 8762.03 | O22: =+H22*N22 -> 8762.03 | P22: 9630.68 | Q22: 4353.72 | R22: 18041 | S22: 13984.4 | T22: 11480.59 | U22: 0.5541 | V22: 10612.2 | W22: 0.3959 | X22: 0.33
A23: 13231 | B23: HECTOR VELA | C23: INDO-MIM MEXICO | D23: 46168 | E23: VENTA DE ACCESORIOS PARA CHAROLA (CHAROFIL) | F23: MXN | G23: 17.3593 | H23: 1 | I23: 1878.67 | J23: =+I23*H23 -> 1878.67 | K23: 529.2 | L23: 529.2 | M23: 0 | N23: 973.4 | O23: =+H23*N23 -> 973.4 | P23: 905.27 | Q23: 0 | R23: 905.27 | S23: 905.27 | T23: 376.07 | U23: 0.4819 | V23: 376.07 | W23: 0.2002 | X23: 0.93
A24: 13228 | B24: ALFREDO PALOMINO | C24: ALCOM ELECTRONICOS DE MEXICO | D24: 46153 | E24: Cotizar Accesorios para mesa de Juntas | F24: MXN | G24: 17.4157 | H24: 1 | I24: 2236.8 | J24: =+I24*H24 -> 2236.8 | K24: 473.68 | L24: 479.76 | M24: 0 | N24: 1436 | O24: =+H24*N24 -> 1436 | P24: 800.8 | Q24: 0 | R24: 800.8 | S24: 758.82 | T24: 279.06 | U24: 0.1248 | V24: 279.06 | W24: 0.1248 | X24: 0.6
A25: 13219 | B25: CELESTE LANDA | C25: MIKUNI MEXICANA | D25: 46153 | E25: MRORC26-1334_M.M | F25: MXN | G25: 17.758 | H25: 1 | I25: 35391.2 | J25: =+I25*H25 -> 35391.2 | K25: 3218.29 | L25: 3034.55 | M25: 0 | N25: 21419.58 | O25: =+H25*N25 -> 21419.58 | P25: 13971.62 | Q25: 0 | R25: 13971.62 | S25: 13971.62 | T25: 10937.07 | U25: 0.4 | V25: 10753.33 | W25: 0.3038 | X25: 0.55
A26: 13173 | B26: HECTOR VELA | C26: VEXIN GLOBAL SUPPLY | D26: 46169 | E26: VENTA DE MONTAJE DE PISO MOBIL DE 86" A 98" (HIKVISION) | F26: MXN | G26: 17.778 | H26: 1 | I26: 7151.29 | J26: =+I26*H26 -> 7151.29 | K26: 558.92 | L26: 555.98 | M26: 0 | N26: 5199.42 | O26: =+H26*N26 -> 5199.42 | P26: 1951.87 | Q26: 0 | R26: 1951.87 | S26: 1951.87 | T26: 1395.89 | U26: 0.2734 | V26: 1392.95 | W26: 0.1948 | X26: 0.35
A27: 13170 | B27: ANA MARGARITA SAHAGUN | C27: CORNING OPTICAL COMMUNICATIONS | D27: 46156 | E27: Goods Plant:RY1 #RFQReq:217440 #Vendor:252542# | F27: MXN | G27: 17.778 | H27: 1 | I27: 3035.18 | J27: =+I27*H27 -> 3035.18 | K27: 550.35 | L27: 451.8 | M27: 0 | N27: 1062.06 | O27: =+H27*N27 -> 1062.06 | P27: 1973.12 | Q27: 0 | R27: 1973.12 | S27: 1973.12 | T27: 1521.32 | U27: 0.6826 | V27: 1422.77 | W27: 0.4688 | X27: 0.92
A28: 13008 | B28: ALFREDO PALOMINO | C28: ALPS ALPINE NORTH AMERICA | D28: 46161 | E28: COTIZACION VS-BX5100 SECURITY CAMERA | F28: USD | G28: 17.2162 | H28: 17.2162 | I28: 426.99 | J28: =+G28*I28 -> 7351.1452 | K28: 55.92 | L28: 51 | M28: 0 | N28: 228 | O28: =+H28*N28 -> 3925.2936 | P28: 198.99 | Q28: 0 | R28: 198.99 | S28: 135.52 | T28: 84.52 | U28: 0.3289 | V28: 79.6 | W28: 0.1864 | X28: 0.65
G29: =+AVERAGE(G2:G28) -> 17.3922 | N29: 287245.77 | O29: =SUM(O2:O28) -> 291171.06
N30: =+N28 -> 228
N31: =+N29+N30*#REF! -> #REF!
J33: =SUBTOTAL(9,J2:J32) -> 1471.5
